{
    "title": "1992 German Grand Prix | Pitwall",
    "race_name": "1992German Grand Prix",
    "round": "10/16",
    "date": "Jul 26, 1992 at 00:00 CEST",
    "location": "Hockenheim, Germany",
    "circuit": "Hockenheimring",
    "circuit_length": "6.815 m",
    "race_distance": "306.675 km (45 laps)",
    "performance": {
        "winner": "Mansell",
        "winning_time": "1:18:22.032",
        "pole_position": "Mansell",
        "fastest_lap": "Patrese",
        "fastest_lap_time": "1:41.591"
    },
    "results": {
        "race": [
            {
                "Pos.": "1",
                "Driver": "#5Nigel Mansell",
                "Constructor": "Williams",
                "Time/Retired": "1:18:22.032",
                "Grid": "1st",
                "Laps": "45",
                "Points": "10"
            },
            {
                "Pos.": "2",
                "Driver": "#1Ayrton Senna",
                "Constructor": "McLaren",
                "Time/Retired": "+4.500",
                "Grid": "3rd",
                "Laps": "45",
                "Points": "6"
            },
            {
                "Pos.": "3",
                "Driver": "#19Michael Schumacher",
                "Constructor": "Benetton",
                "Time/Retired": "+34.462",
                "Grid": "6th",
                "Laps": "45",
                "Points": "4"
            },
            {
                "Pos.": "4",
                "Driver": "#20Martin Brundle",
                "Constructor": "Benetton",
                "Time/Retired": "+36.959",
                "Grid": "9th",
                "Laps": "45",
                "Points": "3"
            },
            {
                "Pos.": "5",
                "Driver": "#27Jean Alesi",
                "Constructor": "Ferrari",
                "Time/Retired": "+1:12.607",
                "Grid": "5th",
                "Laps": "45",
                "Points": "2"
            },
            {
                "Pos.": "6",
                "Driver": "#26Érik Comas",
                "Constructor": "Ligier",
                "Time/Retired": "+1:36.498",
                "Grid": "7th",
                "Laps": "45",
                "Points": "1"
            },
            {
                "Pos.": "7",
                "Driver": "#25Thierry Boutsen",
                "Constructor": "Ligier",
                "Time/Retired": "+1:37.180",
                "Grid": "8th",
                "Laps": "45",
                "Points": ""
            },
            {
                "Pos.": "8",
                "Driver": "#6Riccardo Patrese",
                "Constructor": "Williams",
                "Time/Retired": "+1 lap",
                "Grid": "2nd",
                "Laps": "44",
                "Points": ""
            },
            {
                "Pos.": "9",
                "Driver": "#9Michele Alboreto",
                "Constructor": "Footwork",
                "Time/Retired": "+1 lap",
                "Grid": "17th",
                "Laps": "44",
                "Points": ""
            },
            {
                "Pos.": "10",
                "Driver": "#21JJ Lehto",
                "Constructor": "Dallara",
                "Time/Retired": "+1 lap",
                "Grid": "21st",
                "Laps": "44",
                "Points": ""
            },
            {
                "Pos.": "11",
                "Driver": "#22Pierluigi Martini",
                "Constructor": "Dallara",
                "Time/Retired": "+1 lap",
                "Grid": "18th",
                "Laps": "44",
                "Points": ""
            },
            {
                "Pos.": "12",
                "Driver": "#24Gianni Morbidelli",
                "Constructor": "Minardi",
                "Time/Retired": "+1 lap",
                "Grid": "26th",
                "Laps": "44",
                "Points": ""
            },
            {
                "Pos.": "13",
                "Driver": "#17Paul Belmondo",
                "Constructor": "March",
                "Time/Retired": "+1 lap",
                "Grid": "22nd",
                "Laps": "44",
                "Points": ""
            },
            {
                "Pos.": "14",
                "Driver": "#29Bertrand Gachot",
                "Constructor": "Venturi",
                "Time/Retired": "+1 lap",
                "Grid": "25th",
                "Laps": "44",
                "Points": ""
            },
            {
                "Pos.": "15",
                "Driver": "#33Maurício Gugelmin",
                "Constructor": "Jordan",
                "Time/Retired": "+2 laps",
                "Grid": "23rd",
                "Laps": "43",
                "Points": ""
            },
            {
                "Pos.": "16",
                "Driver": "#16Karl Wendlinger",
                "Constructor": "March",
                "Time/Retired": "+3 laps",
                "Grid": "10th",
                "Laps": "42",
                "Points": ""
            },
            {
                "Pos.": "DNF",
                "Driver": "#15Gabriele Tarquini",
                "Constructor": "Fondmetal",
                "Time/Retired": "Engine",
                "Grid": "19th",
                "Laps": "33",
                "Points": ""
            },
            {
                "Pos.": "DNF",
                "Driver": "#4Andrea de Cesaris",
                "Constructor": "Tyrrell",
                "Time/Retired": "Engine",
                "Grid": "20th",
                "Laps": "25",
                "Points": ""
            },
            {
                "Pos.": "DNF",
                "Driver": "#12Johnny Herbert",
                "Constructor": "Lotus",
                "Time/Retired": "Engine",
                "Grid": "11th",
                "Laps": "23",
                "Points": ""
            },
            {
                "Pos.": "DNF",
                "Driver": "#28Ivan Capelli",
                "Constructor": "Ferrari",
                "Time/Retired": "Engine",
                "Grid": "12th",
                "Laps": "21",
                "Points": ""
            },
            {
                "Pos.": "DNF",
                "Driver": "#11Mika Häkkinen",
                "Constructor": "Lotus",
                "Time/Retired": "Engine",
                "Grid": "13th",
                "Laps": "21",
                "Points": ""
            },
            {
                "Pos.": "DNF",
                "Driver": "#2Gerhard Berger",
                "Constructor": "McLaren",
                "Time/Retired": "Electrical",
                "Grid": "4th",
                "Laps": "16",
                "Points": ""
            },
            {
                "Pos.": "DNF",
                "Driver": "#3Olivier Grouillard",
                "Constructor": "Tyrrell",
                "Time/Retired": "Engine",
                "Grid": "14th",
                "Laps": "8",
                "Points": ""
            },
            {
                "Pos.": "DNF",
                "Driver": "#30Ukyo Katayama",
                "Constructor": "Venturi",
                "Time/Retired": "Spun off",
                "Grid": "16th",
                "Laps": "8",
                "Points": ""
            },
            {
                "Pos.": "DNF",
                "Driver": "#10Aguri Suzuki",
                "Constructor": "Footwork",
                "Time/Retired": "Spun off",
                "Grid": "15th",
                "Laps": "1",
                "Points": ""
            },
            {
                "Pos.": "DNF",
                "Driver": "#23Alex Zanardi",
                "Constructor": "Minardi",
                "Time/Retired": "Gearbox",
                "Grid": "24th",
                "Laps": "1",
                "Points": ""
            },
            {
                "Pos.": "DNQ",
                "Driver": "#32Stefano Modena",
                "Constructor": "Jordan",
                "Time/Retired": "",
                "Grid": "",
                "Laps": "",
                "Points": ""
            },
            {
                "Pos.": "DNQ",
                "Driver": "#7Eric van de Poele",
                "Constructor": "Brabham",
                "Time/Retired": "",
                "Grid": "",
                "Laps": "",
                "Points": ""
            },
            {
                "Pos.": "DNQ",
                "Driver": "#14Andrea Chiesa",
                "Constructor": "Fondmetal",
                "Time/Retired": "",
                "Grid": "",
                "Laps": "",
                "Points": ""
            },
            {
                "Pos.": "DNQ",
                "Driver": "#8Damon Hill",
                "Constructor": "Brabham",
                "Time/Retired": "",
                "Grid": "",
                "Laps": "",
                "Points": ""
            },
            {
                "Pos.": "DNPQ",
                "Driver": "#34Roberto Moreno",
                "Constructor": "Andrea Moda",
                "Time/Retired": "",
                "Grid": "",
                "Laps": "",
                "Points": ""
            },
            {
                "Pos.": "EX",
                "Driver": "#35Perry McCarthy",
                "Constructor": "Andrea Moda",
                "Time/Retired": "",
                "Grid": "",
                "Laps": "",
                "Points": ""
            }
        ],
        "warming_up": [
            {
                "Pos.": "1",
                "Driver": "#5Nigel Mansell",
                "Constructor": "Williams",
                "Time": "1:42.922",
                "Gap": ""
            },
            {
                "Pos.": "2",
                "Driver": "#2Gerhard Berger",
                "Constructor": "McLaren",
                "Time": "1:43.410",
                "Gap": "+0.488"
            },
            {
                "Pos.": "3",
                "Driver": "#6Riccardo Patrese",
                "Constructor": "Williams",
                "Time": "1:43.560",
                "Gap": "+0.638"
            },
            {
                "Pos.": "4",
                "Driver": "#1Ayrton Senna",
                "Constructor": "McLaren",
                "Time": "1:44.251",
                "Gap": "+1.329"
            },
            {
                "Pos.": "5",
                "Driver": "#20Martin Brundle",
                "Constructor": "Benetton",
                "Time": "1:44.555",
                "Gap": "+1.633"
            },
            {
                "Pos.": "6",
                "Driver": "#27Jean Alesi",
                "Constructor": "Ferrari",
                "Time": "1:45.077",
                "Gap": "+2.155"
            },
            {
                "Pos.": "7",
                "Driver": "#19Michael Schumacher",
                "Constructor": "Benetton",
                "Time": "1:45.106",
                "Gap": "+2.184"
            },
            {
                "Pos.": "8",
                "Driver": "#12Johnny Herbert",
                "Constructor": "Lotus",
                "Time": "1:45.490",
                "Gap": "+2.568"
            },
            {
                "Pos.": "9",
                "Driver": "#25Thierry Boutsen",
                "Constructor": "Ligier",
                "Time": "1:45.793",
                "Gap": "+2.871"
            },
            {
                "Pos.": "10",
                "Driver": "#28Ivan Capelli",
                "Constructor": "Ferrari",
                "Time": "1:45.947",
                "Gap": "+3.025"
            },
            {
                "Pos.": "11",
                "Driver": "#11Mika Häkkinen",
                "Constructor": "Lotus",
                "Time": "1:46.200",
                "Gap": "+3.278"
            },
            {
                "Pos.": "12",
                "Driver": "#16Karl Wendlinger",
                "Constructor": "March",
                "Time": "1:46.268",
                "Gap": "+3.346"
            },
            {
                "Pos.": "13",
                "Driver": "#10Aguri Suzuki",
                "Constructor": "Footwork",
                "Time": "1:46.567",
                "Gap": "+3.645"
            },
            {
                "Pos.": "14",
                "Driver": "#26Érik Comas",
                "Constructor": "Ligier",
                "Time": "1:46.689",
                "Gap": "+3.767"
            },
            {
                "Pos.": "15",
                "Driver": "#9Michele Alboreto",
                "Constructor": "Footwork",
                "Time": "1:46.702",
                "Gap": "+3.780"
            },
            {
                "Pos.": "16",
                "Driver": "#29Bertrand Gachot",
                "Constructor": "Venturi",
                "Time": "1:46.992",
                "Gap": "+4.070"
            },
            {
                "Pos.": "17",
                "Driver": "#4Andrea de Cesaris",
                "Constructor": "Tyrrell",
                "Time": "1:46.995",
                "Gap": "+4.073"
            },
            {
                "Pos.": "18",
                "Driver": "#3Olivier Grouillard",
                "Constructor": "Tyrrell",
                "Time": "1:47.244",
                "Gap": "+4.322"
            },
            {
                "Pos.": "19",
                "Driver": "#22Pierluigi Martini",
                "Constructor": "Dallara",
                "Time": "1:47.605",
                "Gap": "+4.683"
            },
            {
                "Pos.": "20",
                "Driver": "#24Gianni Morbidelli",
                "Constructor": "Minardi",
                "Time": "1:47.827",
                "Gap": "+4.905"
            },
            {
                "Pos.": "21",
                "Driver": "#15Gabriele Tarquini",
                "Constructor": "Fondmetal",
                "Time": "1:47.931",
                "Gap": "+5.009"
            },
            {
                "Pos.": "22",
                "Driver": "#17Paul Belmondo",
                "Constructor": "March",
                "Time": "1:48.052",
                "Gap": "+5.130"
            },
            {
                "Pos.": "23",
                "Driver": "#21JJ Lehto",
                "Constructor": "Dallara",
                "Time": "1:48.164",
                "Gap": "+5.242"
            },
            {
                "Pos.": "24",
                "Driver": "#23Alex Zanardi",
                "Constructor": "Minardi",
                "Time": "1:49.929",
                "Gap": "+7.007"
            },
            {
                "Pos.": "25",
                "Driver": "#33Maurício Gugelmin",
                "Constructor": "Jordan",
                "Time": "1:50.326",
                "Gap": "+7.404"
            }
        ],
        "qualifying": [
            {
                "Pos.": "1",
                "Driver": "#5Nigel Mansell",
                "Constructor": "Williams",
                "Time": "1:37.960",
                "Gap": ""
            },
            {
                "Pos.": "2",
                "Driver": "#6Riccardo Patrese",
                "Constructor": "Williams",
                "Time": "1:38.310",
                "Gap": "+0.350"
            },
            {
                "Pos.": "3",
                "Driver": "#1Ayrton Senna",
                "Constructor": "McLaren",
                "Time": "1:39.106",
                "Gap": "+1.146"
            },
            {
                "Pos.": "4",
                "Driver": "#2Gerhard Berger",
                "Constructor": "McLaren",
                "Time": "1:39.716",
                "Gap": "+1.756"
            },
            {
                "Pos.": "5",
                "Driver": "#27Jean Alesi",
                "Constructor": "Ferrari",
                "Time": "1:40.959",
                "Gap": "+2.999"
            },
            {
                "Pos.": "6",
                "Driver": "#19Michael Schumacher",
                "Constructor": "Benetton",
                "Time": "1:41.132",
                "Gap": "+3.172"
            },
            {
                "Pos.": "7",
                "Driver": "#26Érik Comas",
                "Constructor": "Ligier",
                "Time": "1:41.942",
                "Gap": "+3.982"
            },
            {
                "Pos.": "8",
                "Driver": "#25Thierry Boutsen",
                "Constructor": "Ligier",
                "Time": "1:42.112",
                "Gap": "+4.152"
            },
            {
                "Pos.": "9",
                "Driver": "#20Martin Brundle",
                "Constructor": "Benetton",
                "Time": "1:42.136",
                "Gap": "+4.176"
            },
            {
                "Pos.": "10",
                "Driver": "#16Karl Wendlinger",
                "Constructor": "March",
                "Time": "1:42.357",
                "Gap": "+4.397"
            },
            {
                "Pos.": "11",
                "Driver": "#12Johnny Herbert",
                "Constructor": "Lotus",
                "Time": "1:42.645",
                "Gap": "+4.685"
            },
            {
                "Pos.": "12",
                "Driver": "#28Ivan Capelli",
                "Constructor": "Ferrari",
                "Time": "1:42.748",
                "Gap": "+4.788"
            },
            {
                "Pos.": "13",
                "Driver": "#11Mika Häkkinen",
                "Constructor": "Lotus",
                "Time": "1:42.749",
                "Gap": "+4.789"
            },
            {
                "Pos.": "14",
                "Driver": "#3Olivier Grouillard",
                "Constructor": "Tyrrell",
                "Time": "1:42.797",
                "Gap": "+4.837"
            },
            {
                "Pos.": "15",
                "Driver": "#10Aguri Suzuki",
                "Constructor": "Footwork",
                "Time": "1:42.838",
                "Gap": "+4.878"
            },
            {
                "Pos.": "16",
                "Driver": "#30Ukyo Katayama",
                "Constructor": "Venturi",
                "Time": "1:43.079",
                "Gap": "+5.119"
            },
            {
                "Pos.": "17",
                "Driver": "#9Michele Alboreto",
                "Constructor": "Footwork",
                "Time": "1:43.171",
                "Gap": "+5.211"
            },
            {
                "Pos.": "18",
                "Driver": "#22Pierluigi Martini",
                "Constructor": "Dallara",
                "Time": "1:43.556",
                "Gap": "+5.596"
            },
            {
                "Pos.": "19",
                "Driver": "#15Gabriele Tarquini",
                "Constructor": "Fondmetal",
                "Time": "1:43.777",
                "Gap": "+5.817"
            },
            {
                "Pos.": "20",
                "Driver": "#4Andrea de Cesaris",
                "Constructor": "Tyrrell",
                "Time": "1:43.790",
                "Gap": "+5.830"
            },
            {
                "Pos.": "21",
                "Driver": "#21JJ Lehto",
                "Constructor": "Dallara",
                "Time": "1:43.931",
                "Gap": "+5.971"
            },
            {
                "Pos.": "22",
                "Driver": "#17Paul Belmondo",
                "Constructor": "March",
                "Time": "1:44.130",
                "Gap": "+6.170"
            },
            {
                "Pos.": "23",
                "Driver": "#33Maurício Gugelmin",
                "Constructor": "Jordan",
                "Time": "1:44.521",
                "Gap": "+6.561"
            },
            {
                "Pos.": "24",
                "Driver": "#23Alex Zanardi",
                "Constructor": "Minardi",
                "Time": "1:44.593",
                "Gap": "+6.633"
            },
            {
                "Pos.": "25",
                "Driver": "#29Bertrand Gachot",
                "Constructor": "Venturi",
                "Time": "1:44.596",
                "Gap": "+6.636"
            },
            {
                "Pos.": "26",
                "Driver": "#24Gianni Morbidelli",
                "Constructor": "Minardi",
                "Time": "1:44.763",
                "Gap": "+6.803"
            },
            {
                "Pos.": "27",
                "Driver": "#32Stefano Modena",
                "Constructor": "Jordan",
                "Time": "1:45.088",
                "Gap": "+7.128"
            },
            {
                "Pos.": "28",
                "Driver": "#7Eric van de Poele",
                "Constructor": "Brabham",
                "Time": "1:45.098",
                "Gap": "+7.138"
            },
            {
                "Pos.": "29",
                "Driver": "#14Andrea Chiesa",
                "Constructor": "Fondmetal",
                "Time": "1:45.459",
                "Gap": "+7.499"
            },
            {
                "Pos.": "30",
                "Driver": "#8Damon Hill",
                "Constructor": "Brabham",
                "Time": "1:45.871",
                "Gap": "+7.911"
            }
        ],
        "qualifying_2": [
            {
                "Pos.": "1",
                "Driver": "#5Nigel Mansell",
                "Constructor": "Williams",
                "Time": "1:37.960",
                "Gap": ""
            },
            {
                "Pos.": "2",
                "Driver": "#6Riccardo Patrese",
                "Constructor": "Williams",
                "Time": "1:38.310",
                "Gap": "+0.350"
            },
            {
                "Pos.": "3",
                "Driver": "#1Ayrton Senna",
                "Constructor": "McLaren",
                "Time": "1:39.106",
                "Gap": "+1.146"
            },
            {
                "Pos.": "4",
                "Driver": "#2Gerhard Berger",
                "Constructor": "McLaren",
                "Time": "1:39.716",
                "Gap": "+1.756"
            },
            {
                "Pos.": "5",
                "Driver": "#27Jean Alesi",
                "Constructor": "Ferrari",
                "Time": "1:40.959",
                "Gap": "+2.999"
            },
            {
                "Pos.": "6",
                "Driver": "#19Michael Schumacher",
                "Constructor": "Benetton",
                "Time": "1:41.132",
                "Gap": "+3.172"
            },
            {
                "Pos.": "7",
                "Driver": "#26Érik Comas",
                "Constructor": "Ligier",
                "Time": "1:41.942",
                "Gap": "+3.982"
            },
            {
                "Pos.": "8",
                "Driver": "#25Thierry Boutsen",
                "Constructor": "Ligier",
                "Time": "1:42.112",
                "Gap": "+4.152"
            },
            {
                "Pos.": "9",
                "Driver": "#20Martin Brundle",
                "Constructor": "Benetton",
                "Time": "1:42.136",
                "Gap": "+4.176"
            },
            {
                "Pos.": "10",
                "Driver": "#16Karl Wendlinger",
                "Constructor": "March",
                "Time": "1:42.357",
                "Gap": "+4.397"
            },
            {
                "Pos.": "11",
                "Driver": "#12Johnny Herbert",
                "Constructor": "Lotus",
                "Time": "1:42.645",
                "Gap": "+4.685"
            },
            {
                "Pos.": "12",
                "Driver": "#28Ivan Capelli",
                "Constructor": "Ferrari",
                "Time": "1:42.748",
                "Gap": "+4.788"
            },
            {
                "Pos.": "13",
                "Driver": "#11Mika Häkkinen",
                "Constructor": "Lotus",
                "Time": "1:42.749",
                "Gap": "+4.789"
            },
            {
                "Pos.": "14",
                "Driver": "#3Olivier Grouillard",
                "Constructor": "Tyrrell",
                "Time": "1:42.797",
                "Gap": "+4.837"
            },
            {
                "Pos.": "15",
                "Driver": "#10Aguri Suzuki",
                "Constructor": "Footwork",
                "Time": "1:42.838",
                "Gap": "+4.878"
            },
            {
                "Pos.": "16",
                "Driver": "#30Ukyo Katayama",
                "Constructor": "Venturi",
                "Time": "1:43.079",
                "Gap": "+5.119"
            },
            {
                "Pos.": "17",
                "Driver": "#9Michele Alboreto",
                "Constructor": "Footwork",
                "Time": "1:43.171",
                "Gap": "+5.211"
            },
            {
                "Pos.": "18",
                "Driver": "#22Pierluigi Martini",
                "Constructor": "Dallara",
                "Time": "1:43.556",
                "Gap": "+5.596"
            },
            {
                "Pos.": "19",
                "Driver": "#15Gabriele Tarquini",
                "Constructor": "Fondmetal",
                "Time": "1:43.777",
                "Gap": "+5.817"
            },
            {
                "Pos.": "20",
                "Driver": "#21JJ Lehto",
                "Constructor": "Dallara",
                "Time": "1:43.931",
                "Gap": "+5.971"
            },
            {
                "Pos.": "21",
                "Driver": "#17Paul Belmondo",
                "Constructor": "March",
                "Time": "1:44.130",
                "Gap": "+6.170"
            },
            {
                "Pos.": "22",
                "Driver": "#4Andrea de Cesaris",
                "Constructor": "Tyrrell",
                "Time": "1:44.505",
                "Gap": "+6.545"
            },
            {
                "Pos.": "23",
                "Driver": "#33Maurício Gugelmin",
                "Constructor": "Jordan",
                "Time": "1:44.521",
                "Gap": "+6.561"
            },
            {
                "Pos.": "24",
                "Driver": "#23Alex Zanardi",
                "Constructor": "Minardi",
                "Time": "1:44.593",
                "Gap": "+6.633"
            },
            {
                "Pos.": "25",
                "Driver": "#29Bertrand Gachot",
                "Constructor": "Venturi",
                "Time": "1:44.596",
                "Gap": "+6.636"
            },
            {
                "Pos.": "26",
                "Driver": "#24Gianni Morbidelli",
                "Constructor": "Minardi",
                "Time": "1:44.763",
                "Gap": "+6.803"
            },
            {
                "Pos.": "27",
                "Driver": "#32Stefano Modena",
                "Constructor": "Jordan",
                "Time": "1:45.088",
                "Gap": "+7.128"
            },
            {
                "Pos.": "28",
                "Driver": "#7Eric van de Poele",
                "Constructor": "Brabham",
                "Time": "1:45.098",
                "Gap": "+7.138"
            },
            {
                "Pos.": "29",
                "Driver": "#14Andrea Chiesa",
                "Constructor": "Fondmetal",
                "Time": "1:45.459",
                "Gap": "+7.499"
            },
            {
                "Pos.": "30",
                "Driver": "#8Damon Hill",
                "Constructor": "Brabham",
                "Time": "1:45.871",
                "Gap": "+7.911"
            }
        ],
        "qualifying_1": [
            {
                "Pos.": "1",
                "Driver": "#5Nigel Mansell",
                "Constructor": "Williams",
                "Time": "1:38.340",
                "Gap": ""
            },
            {
                "Pos.": "2",
                "Driver": "#1Ayrton Senna",
                "Constructor": "McLaren",
                "Time": "1:40.331",
                "Gap": "+1.991"
            },
            {
                "Pos.": "3",
                "Driver": "#6Riccardo Patrese",
                "Constructor": "Williams",
                "Time": "1:40.501",
                "Gap": "+2.161"
            },
            {
                "Pos.": "4",
                "Driver": "#2Gerhard Berger",
                "Constructor": "McLaren",
                "Time": "1:40.869",
                "Gap": "+2.529"
            },
            {
                "Pos.": "5",
                "Driver": "#19Michael Schumacher",
                "Constructor": "Benetton",
                "Time": "1:42.183",
                "Gap": "+3.843"
            },
            {
                "Pos.": "6",
                "Driver": "#27Jean Alesi",
                "Constructor": "Ferrari",
                "Time": "1:42.563",
                "Gap": "+4.223"
            },
            {
                "Pos.": "7",
                "Driver": "#25Thierry Boutsen",
                "Constructor": "Ligier",
                "Time": "1:42.930",
                "Gap": "+4.590"
            },
            {
                "Pos.": "8",
                "Driver": "#9Michele Alboreto",
                "Constructor": "Footwork",
                "Time": "1:43.574",
                "Gap": "+5.234"
            },
            {
                "Pos.": "9",
                "Driver": "#20Martin Brundle",
                "Constructor": "Benetton",
                "Time": "1:43.614",
                "Gap": "+5.274"
            },
            {
                "Pos.": "10",
                "Driver": "#26Érik Comas",
                "Constructor": "Ligier",
                "Time": "1:43.696",
                "Gap": "+5.356"
            },
            {
                "Pos.": "11",
                "Driver": "#28Ivan Capelli",
                "Constructor": "Ferrari",
                "Time": "1:43.744",
                "Gap": "+5.404"
            },
            {
                "Pos.": "12",
                "Driver": "#4Andrea de Cesaris",
                "Constructor": "Tyrrell",
                "Time": "1:43.790",
                "Gap": "+5.450"
            },
            {
                "Pos.": "13",
                "Driver": "#16Karl Wendlinger",
                "Constructor": "March",
                "Time": "1:44.173",
                "Gap": "+5.833"
            },
            {
                "Pos.": "14",
                "Driver": "#10Aguri Suzuki",
                "Constructor": "Footwork",
                "Time": "1:44.359",
                "Gap": "+6.019"
            },
            {
                "Pos.": "15",
                "Driver": "#11Mika Häkkinen",
                "Constructor": "Lotus",
                "Time": "1:44.370",
                "Gap": "+6.030"
            },
            {
                "Pos.": "16",
                "Driver": "#15Gabriele Tarquini",
                "Constructor": "Fondmetal",
                "Time": "1:44.661",
                "Gap": "+6.321"
            },
            {
                "Pos.": "17",
                "Driver": "#3Olivier Grouillard",
                "Constructor": "Tyrrell",
                "Time": "1:44.689",
                "Gap": "+6.349"
            },
            {
                "Pos.": "18",
                "Driver": "#22Pierluigi Martini",
                "Constructor": "Dallara",
                "Time": "1:45.099",
                "Gap": "+6.759"
            },
            {
                "Pos.": "19",
                "Driver": "#21JJ Lehto",
                "Constructor": "Dallara",
                "Time": "1:45.132",
                "Gap": "+6.792"
            },
            {
                "Pos.": "20",
                "Driver": "#17Paul Belmondo",
                "Constructor": "March",
                "Time": "1:45.190",
                "Gap": "+6.850"
            },
            {
                "Pos.": "21",
                "Driver": "#24Gianni Morbidelli",
                "Constructor": "Minardi",
                "Time": "1:45.455",
                "Gap": "+7.115"
            },
            {
                "Pos.": "22",
                "Driver": "#23Alex Zanardi",
                "Constructor": "Minardi",
                "Time": "1:45.788",
                "Gap": "+7.448"
            },
            {
                "Pos.": "23",
                "Driver": "#33Maurício Gugelmin",
                "Constructor": "Jordan",
                "Time": "1:45.941",
                "Gap": "+7.601"
            },
            {
                "Pos.": "24",
                "Driver": "#12Johnny Herbert",
                "Constructor": "Lotus",
                "Time": "1:46.164",
                "Gap": "+7.824"
            },
            {
                "Pos.": "25",
                "Driver": "#32Stefano Modena",
                "Constructor": "Jordan",
                "Time": "1:46.211",
                "Gap": "+7.871"
            },
            {
                "Pos.": "26",
                "Driver": "#14Andrea Chiesa",
                "Constructor": "Fondmetal",
                "Time": "1:46.362",
                "Gap": "+8.022"
            },
            {
                "Pos.": "27",
                "Driver": "#30Ukyo Katayama",
                "Constructor": "Venturi",
                "Time": "1:46.406",
                "Gap": "+8.066"
            },
            {
                "Pos.": "28",
                "Driver": "#7Eric van de Poele",
                "Constructor": "Brabham",
                "Time": "1:47.321",
                "Gap": "+8.981"
            },
            {
                "Pos.": "29",
                "Driver": "#8Damon Hill",
                "Constructor": "Brabham",
                "Time": "1:49.843",
                "Gap": "+11.503"
            }
        ],
        "pre_qualifying": [
            {
                "Pos.": "1",
                "Driver": "#15Gabriele Tarquini",
                "Constructor": "Fondmetal",
                "Time": "1:45.518",
                "Gap": ""
            },
            {
                "Pos.": "2",
                "Driver": "#29Bertrand Gachot",
                "Constructor": "Venturi",
                "Time": "1:45.766",
                "Gap": "+0.248"
            },
            {
                "Pos.": "3",
                "Driver": "#30Ukyo Katayama",
                "Constructor": "Venturi",
                "Time": "1:46.599",
                "Gap": "+1.081"
            },
            {
                "Pos.": "4",
                "Driver": "#14Andrea Chiesa",
                "Constructor": "Fondmetal",
                "Time": "1:48.502",
                "Gap": "+2.984"
            },
            {
                "Pos.": "5",
                "Driver": "#34Roberto Moreno",
                "Constructor": "Andrea Moda",
                "Time": "1:48.878",
                "Gap": "+3.360"
            },
            {
                "Pos.": "6",
                "Driver": "#35Perry McCarthy",
                "Constructor": "Andrea Moda",
                "Time": "",
                "Gap": ""
            }
        ],
        "free_practice_2": [
            {
                "Pos.": "1",
                "Driver": "#5Nigel Mansell",
                "Constructor": "Williams",
                "Time": "1:37.808",
                "Gap": ""
            },
            {
                "Pos.": "2",
                "Driver": "#6Riccardo Patrese",
                "Constructor": "Williams",
                "Time": "1:39.416",
                "Gap": "+1.608"
            },
            {
                "Pos.": "3",
                "Driver": "#1Ayrton Senna",
                "Constructor": "McLaren",
                "Time": "1:39.756",
                "Gap": "+1.948"
            },
            {
                "Pos.": "4",
                "Driver": "#2Gerhard Berger",
                "Constructor": "McLaren",
                "Time": "1:39.940",
                "Gap": "+2.132"
            },
            {
                "Pos.": "5",
                "Driver": "#20Martin Brundle",
                "Constructor": "Benetton",
                "Time": "1:42.072",
                "Gap": "+4.264"
            },
            {
                "Pos.": "6",
                "Driver": "#27Jean Alesi",
                "Constructor": "Ferrari",
                "Time": "1:42.115",
                "Gap": "+4.307"
            },
            {
                "Pos.": "7",
                "Driver": "#25Thierry Boutsen",
                "Constructor": "Ligier",
                "Time": "1:42.268",
                "Gap": "+4.460"
            },
            {
                "Pos.": "8",
                "Driver": "#3Olivier Grouillard",
                "Constructor": "Tyrrell",
                "Time": "1:42.690",
                "Gap": "+4.882"
            },
            {
                "Pos.": "9",
                "Driver": "#4Andrea de Cesaris",
                "Constructor": "Tyrrell",
                "Time": "1:42.696",
                "Gap": "+4.888"
            },
            {
                "Pos.": "10",
                "Driver": "#10Aguri Suzuki",
                "Constructor": "Footwork",
                "Time": "1:43.040",
                "Gap": "+5.232"
            },
            {
                "Pos.": "11",
                "Driver": "#12Johnny Herbert",
                "Constructor": "Lotus",
                "Time": "1:43.178",
                "Gap": "+5.370"
            },
            {
                "Pos.": "12",
                "Driver": "#26Érik Comas",
                "Constructor": "Ligier",
                "Time": "1:43.314",
                "Gap": "+5.506"
            },
            {
                "Pos.": "13",
                "Driver": "#9Michele Alboreto",
                "Constructor": "Footwork",
                "Time": "1:43.527",
                "Gap": "+5.719"
            },
            {
                "Pos.": "14",
                "Driver": "#21JJ Lehto",
                "Constructor": "Dallara",
                "Time": "1:43.533",
                "Gap": "+5.725"
            },
            {
                "Pos.": "15",
                "Driver": "#19Michael Schumacher",
                "Constructor": "Benetton",
                "Time": "1:43.551",
                "Gap": "+5.743"
            },
            {
                "Pos.": "16",
                "Driver": "#15Gabriele Tarquini",
                "Constructor": "Fondmetal",
                "Time": "1:43.647",
                "Gap": "+5.839"
            },
            {
                "Pos.": "17",
                "Driver": "#22Pierluigi Martini",
                "Constructor": "Dallara",
                "Time": "1:43.781",
                "Gap": "+5.973"
            },
            {
                "Pos.": "18",
                "Driver": "#11Mika Häkkinen",
                "Constructor": "Lotus",
                "Time": "1:43.788",
                "Gap": "+5.980"
            },
            {
                "Pos.": "19",
                "Driver": "#30Ukyo Katayama",
                "Constructor": "Venturi",
                "Time": "1:43.819",
                "Gap": "+6.011"
            },
            {
                "Pos.": "20",
                "Driver": "#16Karl Wendlinger",
                "Constructor": "March",
                "Time": "1:43.854",
                "Gap": "+6.046"
            },
            {
                "Pos.": "21",
                "Driver": "#23Alex Zanardi",
                "Constructor": "Minardi",
                "Time": "1:44.055",
                "Gap": "+6.247"
            },
            {
                "Pos.": "22",
                "Driver": "#24Gianni Morbidelli",
                "Constructor": "Minardi",
                "Time": "1:44.433",
                "Gap": "+6.625"
            },
            {
                "Pos.": "23",
                "Driver": "#17Paul Belmondo",
                "Constructor": "March",
                "Time": "1:44.618",
                "Gap": "+6.810"
            },
            {
                "Pos.": "24",
                "Driver": "#28Ivan Capelli",
                "Constructor": "Ferrari",
                "Time": "1:44.742",
                "Gap": "+6.934"
            },
            {
                "Pos.": "25",
                "Driver": "#32Stefano Modena",
                "Constructor": "Jordan",
                "Time": "1:44.949",
                "Gap": "+7.141"
            },
            {
                "Pos.": "26",
                "Driver": "#14Andrea Chiesa",
                "Constructor": "Fondmetal",
                "Time": "1:45.325",
                "Gap": "+7.517"
            },
            {
                "Pos.": "27",
                "Driver": "#29Bertrand Gachot",
                "Constructor": "Venturi",
                "Time": "1:45.634",
                "Gap": "+7.826"
            },
            {
                "Pos.": "28",
                "Driver": "#33Maurício Gugelmin",
                "Constructor": "Jordan",
                "Time": "1:45.716",
                "Gap": "+7.908"
            },
            {
                "Pos.": "29",
                "Driver": "#7Eric van de Poele",
                "Constructor": "Brabham",
                "Time": "1:45.992",
                "Gap": "+8.184"
            },
            {
                "Pos.": "30",
                "Driver": "#8Damon Hill",
                "Constructor": "Brabham",
                "Time": "1:46.215",
                "Gap": "+8.407"
            }
        ],
        "free_practice_1": [
            {
                "Pos.": "1",
                "Driver": "#5Nigel Mansell",
                "Constructor": "Williams",
                "Time": "1:38.986",
                "Gap": ""
            },
            {
                "Pos.": "2",
                "Driver": "#1Ayrton Senna",
                "Constructor": "McLaren",
                "Time": "1:40.974",
                "Gap": "+1.988"
            },
            {
                "Pos.": "3",
                "Driver": "#2Gerhard Berger",
                "Constructor": "McLaren",
                "Time": "1:41.771",
                "Gap": "+2.785"
            },
            {
                "Pos.": "4",
                "Driver": "#6Riccardo Patrese",
                "Constructor": "Williams",
                "Time": "1:41.849",
                "Gap": "+2.863"
            },
            {
                "Pos.": "5",
                "Driver": "#19Michael Schumacher",
                "Constructor": "Benetton",
                "Time": "1:42.223",
                "Gap": "+3.237"
            },
            {
                "Pos.": "6",
                "Driver": "#27Jean Alesi",
                "Constructor": "Ferrari",
                "Time": "1:43.580",
                "Gap": "+4.594"
            },
            {
                "Pos.": "7",
                "Driver": "#20Martin Brundle",
                "Constructor": "Benetton",
                "Time": "1:43.620",
                "Gap": "+4.634"
            },
            {
                "Pos.": "8",
                "Driver": "#25Thierry Boutsen",
                "Constructor": "Ligier",
                "Time": "1:44.193",
                "Gap": "+5.207"
            },
            {
                "Pos.": "9",
                "Driver": "#4Andrea de Cesaris",
                "Constructor": "Tyrrell",
                "Time": "1:44.319",
                "Gap": "+5.333"
            },
            {
                "Pos.": "10",
                "Driver": "#3Olivier Grouillard",
                "Constructor": "Tyrrell",
                "Time": "1:44.384",
                "Gap": "+5.398"
            },
            {
                "Pos.": "11",
                "Driver": "#10Aguri Suzuki",
                "Constructor": "Footwork",
                "Time": "1:44.499",
                "Gap": "+5.513"
            },
            {
                "Pos.": "12",
                "Driver": "#9Michele Alboreto",
                "Constructor": "Footwork",
                "Time": "1:44.569",
                "Gap": "+5.583"
            },
            {
                "Pos.": "13",
                "Driver": "#26Érik Comas",
                "Constructor": "Ligier",
                "Time": "1:44.609",
                "Gap": "+5.623"
            },
            {
                "Pos.": "14",
                "Driver": "#12Johnny Herbert",
                "Constructor": "Lotus",
                "Time": "1:44.720",
                "Gap": "+5.734"
            },
            {
                "Pos.": "15",
                "Driver": "#16Karl Wendlinger",
                "Constructor": "March",
                "Time": "1:44.971",
                "Gap": "+5.985"
            },
            {
                "Pos.": "16",
                "Driver": "#28Ivan Capelli",
                "Constructor": "Ferrari",
                "Time": "1:45.263",
                "Gap": "+6.277"
            },
            {
                "Pos.": "17",
                "Driver": "#30Ukyo Katayama",
                "Constructor": "Venturi",
                "Time": "1:45.348",
                "Gap": "+6.362"
            },
            {
                "Pos.": "18",
                "Driver": "#17Paul Belmondo",
                "Constructor": "March",
                "Time": "1:45.450",
                "Gap": "+6.464"
            },
            {
                "Pos.": "19",
                "Driver": "#15Gabriele Tarquini",
                "Constructor": "Fondmetal",
                "Time": "1:45.626",
                "Gap": "+6.640"
            },
            {
                "Pos.": "20",
                "Driver": "#22Pierluigi Martini",
                "Constructor": "Dallara",
                "Time": "1:45.638",
                "Gap": "+6.652"
            },
            {
                "Pos.": "21",
                "Driver": "#29Bertrand Gachot",
                "Constructor": "Venturi",
                "Time": "1:45.716",
                "Gap": "+6.730"
            },
            {
                "Pos.": "22",
                "Driver": "#21JJ Lehto",
                "Constructor": "Dallara",
                "Time": "1:46.001",
                "Gap": "+7.015"
            },
            {
                "Pos.": "23",
                "Driver": "#24Gianni Morbidelli",
                "Constructor": "Minardi",
                "Time": "1:46.019",
                "Gap": "+7.033"
            },
            {
                "Pos.": "24",
                "Driver": "#23Alex Zanardi",
                "Constructor": "Minardi",
                "Time": "1:46.151",
                "Gap": "+7.165"
            },
            {
                "Pos.": "25",
                "Driver": "#11Mika Häkkinen",
                "Constructor": "Lotus",
                "Time": "1:46.179",
                "Gap": "+7.193"
            },
            {
                "Pos.": "26",
                "Driver": "#14Andrea Chiesa",
                "Constructor": "Fondmetal",
                "Time": "1:47.172",
                "Gap": "+8.186"
            },
            {
                "Pos.": "27",
                "Driver": "#33Maurício Gugelmin",
                "Constructor": "Jordan",
                "Time": "1:47.285",
                "Gap": "+8.299"
            },
            {
                "Pos.": "28",
                "Driver": "#32Stefano Modena",
                "Constructor": "Jordan",
                "Time": "1:47.308",
                "Gap": "+8.322"
            },
            {
                "Pos.": "29",
                "Driver": "#7Eric van de Poele",
                "Constructor": "Brabham",
                "Time": "1:48.256",
                "Gap": "+9.270"
            },
            {
                "Pos.": "30",
                "Driver": "#8Damon Hill",
                "Constructor": "Brabham",
                "Time": "1:48.326",
                "Gap": "+9.340"
            }
        ],
        "fastest_laps": [
            {
                "Pos.": "1",
                "Driver": "#6Riccardo Patrese",
                "Constructor": "Williams",
                "Time": "1:41.591",
                "Gap": "",
                "Lap": "36"
            },
            {
                "Pos.": "2",
                "Driver": "#1Ayrton Senna",
                "Constructor": "McLaren",
                "Time": "1:42.272",
                "Gap": "+0.681",
                "Lap": "44"
            },
            {
                "Pos.": "3",
                "Driver": "#5Nigel Mansell",
                "Constructor": "Williams",
                "Time": "1:42.379",
                "Gap": "+0.788",
                "Lap": "29"
            },
            {
                "Pos.": "4",
                "Driver": "#20Martin Brundle",
                "Constructor": "Benetton",
                "Time": "1:43.246",
                "Gap": "+1.655",
                "Lap": "39"
            },
            {
                "Pos.": "5",
                "Driver": "#19Michael Schumacher",
                "Constructor": "Benetton",
                "Time": "1:43.690",
                "Gap": "+2.099",
                "Lap": "23"
            },
            {
                "Pos.": "6",
                "Driver": "#25Thierry Boutsen",
                "Constructor": "Ligier",
                "Time": "1:43.944",
                "Gap": "+2.353",
                "Lap": "39"
            },
            {
                "Pos.": "7",
                "Driver": "#27Jean Alesi",
                "Constructor": "Ferrari",
                "Time": "1:44.099",
                "Gap": "+2.508",
                "Lap": "38"
            },
            {
                "Pos.": "8",
                "Driver": "#26Érik Comas",
                "Constructor": "Ligier",
                "Time": "1:44.453",
                "Gap": "+2.862",
                "Lap": "41"
            },
            {
                "Pos.": "9",
                "Driver": "#11Mika Häkkinen",
                "Constructor": "Lotus",
                "Time": "1:44.777",
                "Gap": "+3.186",
                "Lap": "18"
            },
            {
                "Pos.": "10",
                "Driver": "#2Gerhard Berger",
                "Constructor": "McLaren",
                "Time": "1:44.811",
                "Gap": "+3.220",
                "Lap": "13"
            },
            {
                "Pos.": "11",
                "Driver": "#22Pierluigi Martini",
                "Constructor": "Dallara",
                "Time": "1:45.382",
                "Gap": "+3.791",
                "Lap": "38"
            },
            {
                "Pos.": "12",
                "Driver": "#9Michele Alboreto",
                "Constructor": "Footwork",
                "Time": "1:45.474",
                "Gap": "+3.883",
                "Lap": "37"
            },
            {
                "Pos.": "13",
                "Driver": "#17Paul Belmondo",
                "Constructor": "March",
                "Time": "1:45.496",
                "Gap": "+3.905",
                "Lap": "38"
            },
            {
                "Pos.": "14",
                "Driver": "#29Bertrand Gachot",
                "Constructor": "Venturi",
                "Time": "1:45.514",
                "Gap": "+3.923",
                "Lap": "41"
            },
            {
                "Pos.": "15",
                "Driver": "#21JJ Lehto",
                "Constructor": "Dallara",
                "Time": "1:45.517",
                "Gap": "+3.926",
                "Lap": "41"
            },
            {
                "Pos.": "16",
                "Driver": "#15Gabriele Tarquini",
                "Constructor": "Fondmetal",
                "Time": "1:45.586",
                "Gap": "+3.995",
                "Lap": "31"
            },
            {
                "Pos.": "17",
                "Driver": "#12Johnny Herbert",
                "Constructor": "Lotus",
                "Time": "1:45.656",
                "Gap": "+4.065",
                "Lap": "23"
            },
            {
                "Pos.": "18",
                "Driver": "#24Gianni Morbidelli",
                "Constructor": "Minardi",
                "Time": "1:45.825",
                "Gap": "+4.234",
                "Lap": "34"
            },
            {
                "Pos.": "19",
                "Driver": "#16Karl Wendlinger",
                "Constructor": "March",
                "Time": "1:46.023",
                "Gap": "+4.432",
                "Lap": "23"
            },
            {
                "Pos.": "20",
                "Driver": "#28Ivan Capelli",
                "Constructor": "Ferrari",
                "Time": "1:46.029",
                "Gap": "+4.438",
                "Lap": "12"
            },
            {
                "Pos.": "21",
                "Driver": "#4Andrea de Cesaris",
                "Constructor": "Tyrrell",
                "Time": "1:46.820",
                "Gap": "+5.229",
                "Lap": "22"
            },
            {
                "Pos.": "22",
                "Driver": "#33Maurício Gugelmin",
                "Constructor": "Jordan",
                "Time": "1:48.450",
                "Gap": "+6.859",
                "Lap": "42"
            },
            {
                "Pos.": "23",
                "Driver": "#3Olivier Grouillard",
                "Constructor": "Tyrrell",
                "Time": "1:48.489",
                "Gap": "+6.898",
                "Lap": "7"
            },
            {
                "Pos.": "24",
                "Driver": "#30Ukyo Katayama",
                "Constructor": "Venturi",
                "Time": "1:48.639",
                "Gap": "+7.048",
                "Lap": "8"
            },
            {
                "Pos.": "25",
                "Driver": "#10Aguri Suzuki",
                "Constructor": "Footwork",
                "Time": "2:03.333",
                "Gap": "+21.742",
                "Lap": "1"
            },
            {
                "Pos.": "26",
                "Driver": "#23Alex Zanardi",
                "Constructor": "Minardi",
                "Time": "2:33.909",
                "Gap": "+52.318",
                "Lap": "1"
            }
        ],
        "driver": [
            {
                "Pos.": "1",
                "Driver": "Nigel Mansell",
                "Constructor": "Williams",
                "Wins": "8",
                "Podiums": "9",
                "Points": "86",
                "Gap": ""
            },
            {
                "Pos.": "2",
                "Driver": "Riccardo Patrese",
                "Constructor": "Williams",
                "Wins": "0",
                "Podiums": "7",
                "Points": "40",
                "Gap": "-46"
            },
            {
                "Pos.": "3",
                "Driver": "Michael Schumacher",
                "Constructor": "Benetton",
                "Wins": "0",
                "Podiums": "5",
                "Points": "33",
                "Gap": "-53"
            },
            {
                "Pos.": "4",
                "Driver": "Ayrton Senna",
                "Constructor": "McLaren",
                "Wins": "1",
                "Podiums": "4",
                "Points": "24",
                "Gap": "-62"
            },
            {
                "Pos.": "5",
                "Driver": "Gerhard Berger",
                "Constructor": "McLaren",
                "Wins": "1",
                "Podiums": "1",
                "Points": "20",
                "Gap": "-66"
            },
            {
                "Pos.": "6",
                "Driver": "Martin Brundle",
                "Constructor": "Benetton",
                "Wins": "0",
                "Podiums": "2",
                "Points": "16",
                "Gap": "-70"
            },
            {
                "Pos.": "7",
                "Driver": "Jean Alesi",
                "Constructor": "Ferrari",
                "Wins": "0",
                "Podiums": "2",
                "Points": "13",
                "Gap": "-73"
            },
            {
                "Pos.": "8",
                "Driver": "Mika Häkkinen",
                "Constructor": "Lotus",
                "Wins": "0",
                "Podiums": "0",
                "Points": "5",
                "Gap": "-81"
            },
            {
                "Pos.": "9",
                "Driver": "Michele Alboreto",
                "Constructor": "Footwork",
                "Wins": "0",
                "Podiums": "0",
                "Points": "5",
                "Gap": "-81"
            },
            {
                "Pos.": "10",
                "Driver": "Andrea de Cesaris",
                "Constructor": "Tyrrell",
                "Wins": "0",
                "Podiums": "0",
                "Points": "4",
                "Gap": "-82"
            },
            {
                "Pos.": "11",
                "Driver": "Érik Comas",
                "Constructor": "Ligier",
                "Wins": "0",
                "Podiums": "0",
                "Points": "4",
                "Gap": "-82"
            },
            {
                "Pos.": "12",
                "Driver": "Karl Wendlinger",
                "Constructor": "March",
                "Wins": "0",
                "Podiums": "0",
                "Points": "3",
                "Gap": "-83"
            },
            {
                "Pos.": "13",
                "Driver": "Ivan Capelli",
                "Constructor": "Ferrari",
                "Wins": "0",
                "Podiums": "0",
                "Points": "2",
                "Gap": "-84"
            },
            {
                "Pos.": "14",
                "Driver": "Pierluigi Martini",
                "Constructor": "Dallara",
                "Wins": "0",
                "Podiums": "0",
                "Points": "2",
                "Gap": "-84"
            },
            {
                "Pos.": "15",
                "Driver": "Johnny Herbert",
                "Constructor": "Lotus",
                "Wins": "0",
                "Podiums": "0",
                "Points": "2",
                "Gap": "-84"
            },
            {
                "Pos.": "16",
                "Driver": "Bertrand Gachot",
                "Constructor": "Venturi",
                "Wins": "0",
                "Podiums": "0",
                "Points": "1",
                "Gap": "-85"
            }
        ],
        "constructor": [
            {
                "Pos.": "1",
                "Constructor": "Williams",
                "Engine": "Renault",
                "Wins": "8",
                "Podiums": "16",
                "Points": "126",
                "Gap": ""
            },
            {
                "Pos.": "2",
                "Constructor": "Benetton",
                "Engine": "Ford",
                "Wins": "0",
                "Podiums": "7",
                "Points": "49",
                "Gap": "-77"
            },
            {
                "Pos.": "3",
                "Constructor": "McLaren",
                "Engine": "Honda",
                "Wins": "2",
                "Podiums": "5",
                "Points": "44",
                "Gap": "-82"
            },
            {
                "Pos.": "4",
                "Constructor": "Ferrari",
                "Engine": "Ferrari",
                "Wins": "0",
                "Podiums": "2",
                "Points": "15",
                "Gap": "-111"
            },
            {
                "Pos.": "5",
                "Constructor": "Lotus",
                "Engine": "Ford",
                "Wins": "0",
                "Podiums": "0",
                "Points": "7",
                "Gap": "-119"
            },
            {
                "Pos.": "6",
                "Constructor": "Footwork",
                "Engine": "Mugen-Honda",
                "Wins": "0",
                "Podiums": "0",
                "Points": "5",
                "Gap": "-121"
            },
            {
                "Pos.": "7",
                "Constructor": "Tyrrell",
                "Engine": "Ilmor",
                "Wins": "0",
                "Podiums": "0",
                "Points": "4",
                "Gap": "-122"
            },
            {
                "Pos.": "8",
                "Constructor": "Ligier",
                "Engine": "Renault",
                "Wins": "0",
                "Podiums": "0",
                "Points": "4",
                "Gap": "-122"
            },
            {
                "Pos.": "9",
                "Constructor": "March",
                "Engine": "Ilmor",
                "Wins": "0",
                "Podiums": "0",
                "Points": "3",
                "Gap": "-123"
            },
            {
                "Pos.": "10",
                "Constructor": "Dallara",
                "Engine": "Ferrari",
                "Wins": "0",
                "Podiums": "0",
                "Points": "2",
                "Gap": "-124"
            },
            {
                "Pos.": "11",
                "Constructor": "Venturi",
                "Engine": "Lamborghini",
                "Wins": "0",
                "Podiums": "0",
                "Points": "1",
                "Gap": "-125"
            },
            {
                "Year": "2019",
                "Winner": "#33Max Verstappen",
                "2nd": "Sebastian Vettel",
                "3rd": "Daniil Kvyat",
                "Fastest lap": "1:16.645 - Max Verstappen",
                "Pole position": "Lewis Hamilton"
            },
            {
                "Year": "2018",
                "Winner": "#44Lewis Hamilton",
                "2nd": "Valtteri Bottas",
                "3rd": "Kimi Räikkönen",
                "Fastest lap": "1:15.545 - Lewis Hamilton",
                "Pole position": "Sebastian Vettel"
            },
            {
                "Year": "2016",
                "Winner": "#44Lewis Hamilton",
                "2nd": "Daniel Ricciardo",
                "3rd": "Max Verstappen",
                "Fastest lap": "1:18.442 - Daniel Ricciardo",
                "Pole position": "Nico Rosberg"
            },
            {
                "Year": "2014",
                "Winner": "#6Nico Rosberg",
                "2nd": "Valtteri Bottas",
                "3rd": "Lewis Hamilton",
                "Fastest lap": "1:19.908 - Lewis Hamilton",
                "Pole position": "Nico Rosberg"
            },
            {
                "Year": "2013",
                "Winner": "#1Sebastian Vettel",
                "2nd": "Kimi Räikkönen",
                "3rd": "Romain Grosjean",
                "Fastest lap": "1:33.468 - Fernando Alonso",
                "Pole position": "Lewis Hamilton"
            },
            {
                "Year": "2012",
                "Winner": "#5Fernando Alonso",
                "2nd": "Jenson Button",
                "3rd": "Kimi Räikkönen",
                "Fastest lap": "1:18.725 - Michael Schumacher",
                "Pole position": "Fernando Alonso"
            },
            {
                "Year": "2011",
                "Winner": "#3Lewis Hamilton",
                "2nd": "Fernando Alonso",
                "3rd": "Mark Webber",
                "Fastest lap": "1:34.302 - Lewis Hamilton",
                "Pole position": "Mark Webber"
            },
            {
                "Year": "2010",
                "Winner": "#8Fernando Alonso",
                "2nd": "Felipe Massa",
                "3rd": "Sebastian Vettel",
                "Fastest lap": "1:15.824 - Sebastian Vettel",
                "Pole position": "Sebastian Vettel"
            },
            {
                "Year": "2009",
                "Winner": "#14Mark Webber",
                "2nd": "Sebastian Vettel",
                "3rd": "Felipe Massa",
                "Fastest lap": "1:33.365 - Fernando Alonso",
                "Pole position": "Mark Webber"
            },
            {
                "Year": "2008",
                "Winner": "#22Lewis Hamilton",
                "2nd": "Nelson Piquet Jr.",
                "3rd": "Felipe Massa",
                "Fastest lap": "1:15.987 - Nick Heidfeld",
                "Pole position": "Lewis Hamilton"
            },
            {
                "Year": "2006",
                "Winner": "#5Michael Schumacher",
                "2nd": "Felipe Massa",
                "3rd": "Kimi Räikkönen",
                "Fastest lap": "1:16.357 - Michael Schumacher",
                "Pole position": "Kimi Räikkönen"
            },
            {
                "Year": "2005",
                "Winner": "#5Fernando Alonso",
                "2nd": "Juan Pablo Montoya",
                "3rd": "Jenson Button",
                "Fastest lap": "1:14.873 - Kimi Räikkönen",
                "Pole position": "Kimi Räikkönen"
            },
            {
                "Year": "2004",
                "Winner": "#1Michael Schumacher",
                "2nd": "Jenson Button",
                "3rd": "Fernando Alonso",
                "Fastest lap": "1:13.780 - Kimi Räikkönen",
                "Pole position": "Michael Schumacher"
            },
            {
                "Year": "2003",
                "Winner": "#3Juan Pablo Montoya",
                "2nd": "David Coulthard",
                "3rd": "Jarno Trulli",
                "Fastest lap": "1:14.917 - Juan Pablo Montoya",
                "Pole position": "Juan Pablo Montoya"
            },
            {
                "Year": "2002",
                "Winner": "#1Michael Schumacher",
                "2nd": "Juan Pablo Montoya",
                "3rd": "Ralf Schumacher",
                "Fastest lap": "1:16.462 - Michael Schumacher",
                "Pole position": "Michael Schumacher"
            },
            {
                "Year": "2001",
                "Winner": "#5Ralf Schumacher",
                "2nd": "Rubens Barrichello",
                "3rd": "Jacques Villeneuve",
                "Fastest lap": "1:41.808 - Juan Pablo Montoya",
                "Pole position": "Juan Pablo Montoya"
            },
            {
                "Year": "2000",
                "Winner": "#4Rubens Barrichello",
                "2nd": "Mika Häkkinen",
                "3rd": "David Coulthard",
                "Fastest lap": "1:44.300 - Rubens Barrichello",
                "Pole position": "David Coulthard"
            },
            {
                "Year": "1999",
                "Winner": "#4Eddie Irvine",
                "2nd": "Mika Salo",
                "3rd": "Heinz-Harald Frentzen",
                "Fastest lap": "1:45.270 - David Coulthard",
                "Pole position": "Mika Häkkinen"
            },
            {
                "Year": "1998",
                "Winner": "#8Mika Häkkinen",
                "2nd": "David Coulthard",
                "3rd": "Jacques Villeneuve",
                "Fastest lap": "1:46.116 - David Coulthard",
                "Pole position": "Mika Häkkinen"
            },
            {
                "Year": "1997",
                "Winner": "#8Gerhard Berger",
                "2nd": "Michael Schumacher",
                "3rd": "Mika Häkkinen",
                "Fastest lap": "1:45.747 - Gerhard Berger",
                "Pole position": "Gerhard Berger"
            },
            {
                "Year": "1996",
                "Winner": "#5Damon Hill",
                "2nd": "Jean Alesi",
                "3rd": "Jacques Villeneuve",
                "Fastest lap": "1:46.504 - Damon Hill",
                "Pole position": "Damon Hill"
            },
            {
                "Year": "1995",
                "Winner": "#1Michael Schumacher",
                "2nd": "David Coulthard",
                "3rd": "Gerhard Berger",
                "Fastest lap": "1:48.824 - Michael Schumacher",
                "Pole position": "Damon Hill"
            },
            {
                "Year": "1994",
                "Winner": "#28Gerhard Berger",
                "2nd": "Olivier Panis",
                "3rd": "Éric Bernard",
                "Fastest lap": "1:46.211 - David Coulthard",
                "Pole position": "Gerhard Berger"
            },
            {
                "Year": "1993",
                "Winner": "#2Alain Prost",
                "2nd": "Michael Schumacher",
                "3rd": "Mark Blundell",
                "Fastest lap": "1:41.859 - Michael Schumacher",
                "Pole position": "Alain Prost"
            },
            {
                "Year": "1991",
                "Winner": "#5Nigel Mansell",
                "2nd": "Riccardo Patrese",
                "3rd": "Jean Alesi",
                "Fastest lap": "1:43.569 - Riccardo Patrese",
                "Pole position": "Nigel Mansell"
            },
            {
                "Year": "1990",
                "Winner": "#27Ayrton Senna",
                "2nd": "Alessandro Nannini",
                "3rd": "Gerhard Berger",
                "Fastest lap": "1:45.602 - Thierry Boutsen",
                "Pole position": "Ayrton Senna"
            },
            {
                "Year": "1989",
                "Winner": "#1Ayrton Senna",
                "2nd": "Alain Prost",
                "3rd": "Nigel Mansell",
                "Fastest lap": "1:45.884 - Ayrton Senna",
                "Pole position": "Ayrton Senna"
            },
            {
                "Year": "1988",
                "Winner": "#12Ayrton Senna",
                "2nd": "Alain Prost",
                "3rd": "Gerhard Berger",
                "Fastest lap": "2:03.032 - Alessandro Nannini",
                "Pole position": "Ayrton Senna"
            },
            {
                "Year": "1987",
                "Winner": "#6Nelson Piquet",
                "2nd": "Stefan Johansson",
                "3rd": "Ayrton Senna",
                "Fastest lap": "1:45.716 - Nigel Mansell",
                "Pole position": "Nigel Mansell"
            },
            {
                "Year": "1986",
                "Winner": "#6Nelson Piquet",
                "2nd": "Ayrton Senna",
                "3rd": "Nigel Mansell",
                "Fastest lap": "1:46.604 - Gerhard Berger",
                "Pole position": "Keke Rosberg"
            },
            {
                "Year": "1985",
                "Winner": "#27Michele Alboreto",
                "2nd": "Alain Prost",
                "3rd": "Jacques Laffite",
                "Fastest lap": "1:22.806 - Niki Lauda",
                "Pole position": "Teo Fabi"
            },
            {
                "Year": "1984",
                "Winner": "#7Alain Prost",
                "2nd": "Niki Lauda",
                "3rd": "Derek Warwick",
                "Fastest lap": "1:53.538 - Alain Prost",
                "Pole position": "Alain Prost"
            },
            {
                "Year": "1983",
                "Winner": "#28René Arnoux",
                "2nd": "Andrea de Cesaris",
                "3rd": "Riccardo Patrese",
                "Fastest lap": "1:53.938 - René Arnoux",
                "Pole position": "Patrick Tambay"
            },
            {
                "Year": "1982",
                "Winner": "#27Patrick Tambay",
                "2nd": "René Arnoux",
                "3rd": "Keke Rosberg",
                "Fastest lap": "1:54.035 - Nelson Piquet",
                "Pole position": "Didier Pironi"
            },
            {
                "Year": "1981",
                "Winner": "#5Nelson Piquet",
                "2nd": "Alain Prost",
                "3rd": "Jacques Laffite",
                "Fastest lap": "1:52.420 - Alan Jones",
                "Pole position": "Alain Prost"
            },
            {
                "Year": "1980",
                "Winner": "#26Jacques Laffite",
                "2nd": "Carlos Reutemann",
                "3rd": "Alan Jones",
                "Fastest lap": "1:48.490 - Alan Jones",
                "Pole position": "Alan Jones"
            },
            {
                "Year": "1979",
                "Winner": "#27Alan Jones",
                "2nd": "Clay Regazzoni",
                "3rd": "Jacques Laffite",
                "Fastest lap": "1:51.890 - Gilles Villeneuve",
                "Pole position": "Jean-Pierre Jabouille"
            },
            {
                "Year": "1978",
                "Winner": "#5Mario Andretti",
                "2nd": "Jody Scheckter",
                "3rd": "Jacques Laffite",
                "Fastest lap": "1:55.620 - Ronnie Peterson",
                "Pole position": "Mario Andretti"
            },
            {
                "Year": "1977",
                "Winner": "#11Niki Lauda",
                "2nd": "Jody Scheckter",
                "3rd": "Hans-Joachim Stuck",
                "Fastest lap": "1:55.990 - Niki Lauda",
                "Pole position": "Jody Scheckter"
            },
            {
                "Year": "1976",
                "Winner": "#11James Hunt",
                "2nd": "Jody Scheckter",
                "3rd": "Jochen Mass",
                "Fastest lap": "7:10.800 - Jody Scheckter",
                "Pole position": "James Hunt"
            },
            {
                "Year": "1975",
                "Winner": "#7Carlos Reutemann",
                "2nd": "Jacques Laffite",
                "3rd": "Niki Lauda",
                "Fastest lap": "7:06.400 - Clay Regazzoni",
                "Pole position": "Niki Lauda"
            },
            {
                "Year": "1974",
                "Winner": "#11Clay Regazzoni",
                "2nd": "Jody Scheckter",
                "3rd": "Carlos Reutemann",
                "Fastest lap": "7:11.100 - Jody Scheckter",
                "Pole position": "Niki Lauda"
            },
            {
                "Year": "1973",
                "Winner": "#5Jackie Stewart",
                "2nd": "François Cevert",
                "3rd": "Jacky Ickx",
                "Fastest lap": "7:11.400 - Carlos Pace",
                "Pole position": "Jackie Stewart"
            },
            {
                "Year": "1972",
                "Winner": "#4Jacky Ickx",
                "2nd": "Clay Regazzoni",
                "3rd": "Ronnie Peterson",
                "Fastest lap": "7:13.600 - Jacky Ickx",
                "Pole position": "Jacky Ickx"
            },
            {
                "Year": "1971",
                "Winner": "#2Jackie Stewart",
                "2nd": "François Cevert",
                "3rd": "Clay Regazzoni",
                "Fastest lap": "7:20.100 - François Cevert",
                "Pole position": "Jackie Stewart"
            },
            {
                "Year": "1970",
                "Winner": "#2Jochen Rindt",
                "2nd": "Jacky Ickx",
                "3rd": "Denny Hulme",
                "Fastest lap": "2:00.500 - Jacky Ickx",
                "Pole position": "Jacky Ickx"
            },
            {
                "Year": "1969",
                "Winner": "#6Jacky Ickx",
                "2nd": "Jackie Stewart",
                "3rd": "Bruce McLaren",
                "Fastest lap": "7:43.800 - Jacky Ickx",
                "Pole position": "Jacky Ickx"
            },
            {
                "Year": "1968",
                "Winner": "#6Jackie Stewart",
                "2nd": "Graham Hill",
                "3rd": "Jochen Rindt",
                "Fastest lap": "9:36.000 - Jackie Stewart",
                "Pole position": "Jacky Ickx"
            },
            {
                "Year": "1967",
                "Winner": "#2Denny Hulme",
                "2nd": "Jack Brabham",
                "3rd": "Chris Amon",
                "Fastest lap": "8:15.100 - Dan Gurney",
                "Pole position": "Jim Clark"
            },
            {
                "Year": "1966",
                "Winner": "#3Jack Brabham",
                "2nd": "John Surtees",
                "3rd": "Jochen Rindt",
                "Fastest lap": "8:49.000 - John Surtees",
                "Pole position": "Jim Clark"
            },
            {
                "Year": "1965",
                "Winner": "#1Jim Clark",
                "2nd": "Graham Hill",
                "3rd": "Dan Gurney",
                "Fastest lap": "8:24.100 - Jim Clark",
                "Pole position": "Jim Clark"
            },
            {
                "Year": "1964",
                "Winner": "#7John Surtees",
                "2nd": "Graham Hill",
                "3rd": "Lorenzo Bandini",
                "Fastest lap": "8:39.000 - John Surtees",
                "Pole position": "John Surtees"
            },
            {
                "Year": "1963",
                "Winner": "#7John Surtees",
                "2nd": "Jim Clark",
                "3rd": "Richie Ginther",
                "Fastest lap": "8:47.000 - John Surtees",
                "Pole position": "Jim Clark"
            },
            {
                "Year": "1962",
                "Winner": "#11Graham Hill",
                "2nd": "John Surtees",
                "3rd": "Dan Gurney",
                "Fastest lap": "10:12.200 - Graham Hill",
                "Pole position": "Dan Gurney"
            },
            {
                "Year": "1961",
                "Winner": "#7Stirling Moss",
                "2nd": "Wolfgang von Trips",
                "3rd": "Phil Hill",
                "Fastest lap": "8:57.800 - Phil Hill",
                "Pole position": "Phil Hill"
            },
            {
                "Year": "1959",
                "Winner": "#4Tony Brooks",
                "2nd": "Dan Gurney",
                "3rd": "Phil Hill",
                "Fastest lap": "2:04.500 - Tony Brooks",
                "Pole position": "Tony Brooks"
            },
            {
                "Year": "1958",
                "Winner": "#8Tony Brooks",
                "2nd": "Roy Salvadori",
                "3rd": "Maurice Trintignant",
                "Fastest lap": "9:09.200 - Stirling Moss",
                "Pole position": "Mike Hawthorn"
            },
            {
                "Year": "1957",
                "Winner": "#1Juan Manuel Fangio",
                "2nd": "Mike Hawthorn",
                "3rd": "Peter Collins",
                "Fastest lap": "9:17.400 - Juan Manuel Fangio",
                "Pole position": "Juan Manuel Fangio"
            },
            {
                "Year": "1956",
                "Winner": "#1Juan Manuel Fangio",
                "2nd": "Stirling Moss",
                "3rd": "Jean Behra",
                "Fastest lap": "9:41.600 - Juan Manuel Fangio",
                "Pole position": "Juan Manuel Fangio"
            },
            {
                "Year": "1954",
                "Winner": "#18Juan Manuel Fangio",
                "2nd": "José Froilán González",
                "3rd": "Maurice Trintignant",
                "Fastest lap": "9:55.100 - Karl Kling",
                "Pole position": "Juan Manuel Fangio"
            },
            {
                "Year": "1953",
                "Winner": "#2Nino Farina",
                "2nd": "Juan Manuel Fangio",
                "3rd": "Mike Hawthorn",
                "Fastest lap": "9:56.000 - Alberto Ascari",
                "Pole position": "Alberto Ascari"
            },
            {
                "Year": "1952",
                "Winner": "#101Alberto Ascari",
                "2nd": "Nino Farina",
                "3rd": "Rudi Fischer",
                "Fastest lap": "10:05.100 - Alberto Ascari",
                "Pole position": "Alberto Ascari"
            },
            {
                "Year": "1951",
                "Winner": "#71Alberto Ascari",
                "2nd": "Juan Manuel Fangio",
                "3rd": "José Froilán González",
                "Fastest lap": "9:55.800 - Juan Manuel Fangio",
                "Pole position": "Alberto Ascari"
            }
        ]
    }
}