{
    "title": "2016 Hungarian Grand Prix | Pitwall",
    "race_name": "2016Hungarian Grand Prix",
    "round": "11/21",
    "date": "Jul 24, 2016 at 00:00 CEST",
    "location": "Budapest, Hungary",
    "circuit": "Hungaroring",
    "circuit_length": "4.381 m",
    "race_distance": "306.63 km (70 laps)",
    "performance": {
        "winner": "Hamilton",
        "winning_time": "1:40:30.115",
        "pole_position": "Rosberg",
        "fastest_lap": "Räikkönen",
        "fastest_lap_time": "1:23.086",
        "fastest_pitstop": "Button",
        "fastest_pitstop_time": "16.486"
    },
    "results": {
        "race": [
            {
                "Pos.": "1",
                "Driver": "#44Lewis Hamilton",
                "Constructor": "Mercedes",
                "Time/Retired": "1:40:30.115",
                "Grid": "2nd",
                "Laps": "70",
                "Points": "25"
            },
            {
                "Pos.": "2",
                "Driver": "#6Nico Rosberg",
                "Constructor": "Mercedes",
                "Time/Retired": "+1.977",
                "Grid": "1st",
                "Laps": "70",
                "Points": "18"
            },
            {
                "Pos.": "3",
                "Driver": "#3Daniel Ricciardo",
                "Constructor": "Red Bull",
                "Time/Retired": "+27.539",
                "Grid": "3rd",
                "Laps": "70",
                "Points": "15"
            },
            {
                "Pos.": "4",
                "Driver": "#5Sebastian Vettel",
                "Constructor": "Ferrari",
                "Time/Retired": "+28.213",
                "Grid": "5th",
                "Laps": "70",
                "Points": "12"
            },
            {
                "Pos.": "5",
                "Driver": "#33Max Verstappen",
                "Constructor": "Red Bull",
                "Time/Retired": "+48.659",
                "Grid": "4th",
                "Laps": "70",
                "Points": "10"
            },
            {
                "Pos.": "6",
                "Driver": "#7Kimi Räikkönen",
                "Constructor": "Ferrari",
                "Time/Retired": "+49.044",
                "Grid": "14th",
                "Laps": "70",
                "Points": "8"
            },
            {
                "Pos.": "7",
                "Driver": "#14Fernando Alonso",
                "Constructor": "McLaren",
                "Time/Retired": "+1 lap",
                "Grid": "7th",
                "Laps": "69",
                "Points": "6"
            },
            {
                "Pos.": "8",
                "Driver": "#55Carlos Sainz Jr.",
                "Constructor": "Toro Rosso",
                "Time/Retired": "+1 lap",
                "Grid": "6th",
                "Laps": "69",
                "Points": "4"
            },
            {
                "Pos.": "9",
                "Driver": "#77Valtteri Bottas",
                "Constructor": "Williams",
                "Time/Retired": "+1 lap",
                "Grid": "10th",
                "Laps": "69",
                "Points": "2"
            },
            {
                "Pos.": "10",
                "Driver": "#27Nico Hülkenberg",
                "Constructor": "Force India",
                "Time/Retired": "+1 lap",
                "Grid": "9th",
                "Laps": "69",
                "Points": "1"
            },
            {
                "Pos.": "11",
                "Driver": "#11Sergio Pérez",
                "Constructor": "Force India",
                "Time/Retired": "+1 lap",
                "Grid": "13th",
                "Laps": "69",
                "Points": ""
            },
            {
                "Pos.": "12",
                "Driver": "#30Jolyon Palmer",
                "Constructor": "Renault",
                "Time/Retired": "+1 lap",
                "Grid": "17th",
                "Laps": "69",
                "Points": ""
            },
            {
                "Pos.": "13",
                "Driver": "#21Esteban Gutiérrez",
                "Constructor": "Haas",
                "Time/Retired": "+1 lap",
                "Grid": "15th",
                "Laps": "69",
                "Points": ""
            },
            {
                "Pos.": "14",
                "Driver": "#8Romain Grosjean",
                "Constructor": "Haas",
                "Time/Retired": "+1 lap",
                "Grid": "11th",
                "Laps": "69",
                "Points": ""
            },
            {
                "Pos.": "15",
                "Driver": "#20Kevin Magnussen",
                "Constructor": "Renault",
                "Time/Retired": "+1 lap",
                "Grid": "19th",
                "Laps": "69",
                "Points": ""
            },
            {
                "Pos.": "16",
                "Driver": "#26Daniil Kvyat",
                "Constructor": "Toro Rosso",
                "Time/Retired": "+1 lap",
                "Grid": "12th",
                "Laps": "69",
                "Points": ""
            },
            {
                "Pos.": "17",
                "Driver": "#12Felipe Nasr",
                "Constructor": "Sauber",
                "Time/Retired": "+1 lap",
                "Grid": "16th",
                "Laps": "69",
                "Points": ""
            },
            {
                "Pos.": "18",
                "Driver": "#19Felipe Massa",
                "Constructor": "Williams",
                "Time/Retired": "+2 laps",
                "Grid": "18th",
                "Laps": "68",
                "Points": ""
            },
            {
                "Pos.": "19",
                "Driver": "#94Pascal Wehrlein",
                "Constructor": "Manor",
                "Time/Retired": "+2 laps",
                "Grid": "20th",
                "Laps": "68",
                "Points": ""
            },
            {
                "Pos.": "20",
                "Driver": "#9Marcus Ericsson",
                "Constructor": "Sauber",
                "Time/Retired": "+2 laps",
                "Grid": "PL",
                "Laps": "68",
                "Points": ""
            },
            {
                "Pos.": "21",
                "Driver": "#88Rio Haryanto",
                "Constructor": "Manor",
                "Time/Retired": "+2 laps",
                "Grid": "21st",
                "Laps": "68",
                "Points": ""
            },
            {
                "Pos.": "DNF",
                "Driver": "#22Jenson Button",
                "Constructor": "McLaren",
                "Time/Retired": "Oil leak",
                "Grid": "8th",
                "Laps": "60",
                "Points": ""
            }
        ],
        "qualifying": [
            {
                "Pos.": "1",
                "Driver": "#6Nico Rosberg",
                "Constructor": "Mercedes",
                "Q1": "1:33.302",
                "Q2": "1:22.806",
                "Q3": "1:19.965",
                "Gap": "",
                "Laps": "29"
            },
            {
                "Pos.": "2",
                "Driver": "#44Lewis Hamilton",
                "Constructor": "Mercedes",
                "Q1": "1:34.210",
                "Q2": "1:24.836",
                "Q3": "1:20.108",
                "Gap": "+0.143",
                "Laps": "28"
            },
            {
                "Pos.": "3",
                "Driver": "#3Daniel Ricciardo",
                "Constructor": "Red Bull",
                "Q1": "1:39.968",
                "Q2": "1:23.234",
                "Q3": "1:20.280",
                "Gap": "+0.315",
                "Laps": "27"
            },
            {
                "Pos.": "4",
                "Driver": "#33Max Verstappen",
                "Constructor": "Red Bull",
                "Q1": "1:40.424",
                "Q2": "1:22.660",
                "Q3": "1:20.557",
                "Gap": "+0.592",
                "Laps": "27"
            },
            {
                "Pos.": "5",
                "Driver": "#5Sebastian Vettel",
                "Constructor": "Ferrari",
                "Q1": "1:35.718",
                "Q2": "1:24.082",
                "Q3": "1:20.874",
                "Gap": "+0.909",
                "Laps": "25"
            },
            {
                "Pos.": "6",
                "Driver": "#55Carlos Sainz Jr.",
                "Constructor": "Toro Rosso",
                "Q1": "1:36.115",
                "Q2": "1:24.734",
                "Q3": "1:21.131",
                "Gap": "+1.166",
                "Laps": "28"
            },
            {
                "Pos.": "7",
                "Driver": "#14Fernando Alonso",
                "Constructor": "McLaren",
                "Q1": "1:35.165",
                "Q2": "1:23.816",
                "Q3": "1:21.211",
                "Gap": "+1.246",
                "Laps": "28"
            },
            {
                "Pos.": "8",
                "Driver": "#22Jenson Button",
                "Constructor": "McLaren",
                "Q1": "1:37.983",
                "Q2": "1:24.456",
                "Q3": "1:21.597",
                "Gap": "+1.632",
                "Laps": "25"
            },
            {
                "Pos.": "9",
                "Driver": "#27Nico Hülkenberg",
                "Constructor": "Force India",
                "Q1": "1:41.471",
                "Q2": "1:23.901",
                "Q3": "1:21.823",
                "Gap": "+1.858",
                "Laps": "24"
            },
            {
                "Pos.": "10",
                "Driver": "#77Valtteri Bottas",
                "Constructor": "Williams",
                "Q1": "1:42.758",
                "Q2": "1:24.506",
                "Q3": "1:22.182",
                "Gap": "+2.217",
                "Laps": "26"
            },
            {
                "Pos.": "11",
                "Driver": "#8Romain Grosjean",
                "Constructor": "Haas",
                "Q1": "1:35.906",
                "Q2": "1:24.941",
                "Q3": "",
                "Gap": "",
                "Laps": "18"
            },
            {
                "Pos.": "12",
                "Driver": "#26Daniil Kvyat",
                "Constructor": "Toro Rosso",
                "Q1": "1:36.714",
                "Q2": "1:25.301",
                "Q3": "",
                "Gap": "",
                "Laps": "21"
            },
            {
                "Pos.": "13",
                "Driver": "#11Sergio Pérez",
                "Constructor": "Force India",
                "Q1": "1:41.411",
                "Q2": "1:25.416",
                "Q3": "",
                "Gap": "",
                "Laps": "16"
            },
            {
                "Pos.": "14",
                "Driver": "#7Kimi Räikkönen",
                "Constructor": "Ferrari",
                "Q1": "1:36.853",
                "Q2": "1:25.435",
                "Q3": "",
                "Gap": "",
                "Laps": "20"
            },
            {
                "Pos.": "15",
                "Driver": "#21Esteban Gutiérrez",
                "Constructor": "Haas",
                "Q1": "1:38.959",
                "Q2": "1:26.189",
                "Q3": "",
                "Gap": "",
                "Laps": "18"
            },
            {
                "Pos.": "16",
                "Driver": "#12Felipe Nasr",
                "Constructor": "Sauber",
                "Q1": "1:37.772",
                "Q2": "1:27.063",
                "Q3": "",
                "Gap": "",
                "Laps": "21"
            },
            {
                "Pos.": "NC",
                "Driver": "#30Jolyon Palmer",
                "Constructor": "Renault",
                "Q1": "1:43.965",
                "Q2": "",
                "Q3": "",
                "Gap": "",
                "Laps": "9"
            },
            {
                "Pos.": "NC",
                "Driver": "#19Felipe Massa",
                "Constructor": "Williams",
                "Q1": "1:43.999",
                "Q2": "",
                "Q3": "",
                "Gap": "",
                "Laps": "7"
            },
            {
                "Pos.": "NC",
                "Driver": "#20Kevin Magnussen",
                "Constructor": "Renault",
                "Q1": "1:44.543",
                "Q2": "",
                "Q3": "",
                "Gap": "",
                "Laps": "9"
            },
            {
                "Pos.": "NC",
                "Driver": "#9Marcus Ericsson",
                "Constructor": "Sauber",
                "Q1": "1:46.984",
                "Q2": "",
                "Q3": "",
                "Gap": "",
                "Laps": "5"
            },
            {
                "Pos.": "NC",
                "Driver": "#94Pascal Wehrlein",
                "Constructor": "Manor",
                "Q1": "1:47.343",
                "Q2": "",
                "Q3": "",
                "Gap": "",
                "Laps": "9"
            },
            {
                "Pos.": "NC",
                "Driver": "#88Rio Haryanto",
                "Constructor": "Manor",
                "Q1": "1:50.189",
                "Q2": "",
                "Q3": "",
                "Gap": "",
                "Laps": "9"
            }
        ],
        "free_practice_3": [
            {
                "Pos.": "1",
                "Driver": "#6Nico Rosberg",
                "Constructor": "Mercedes",
                "Time": "1:20.261",
                "Gap": "",
                "Laps": "25"
            },
            {
                "Pos.": "2",
                "Driver": "#33Max Verstappen",
                "Constructor": "Red Bull",
                "Time": "1:20.263",
                "Gap": "+0.002",
                "Laps": "10"
            },
            {
                "Pos.": "3",
                "Driver": "#3Daniel Ricciardo",
                "Constructor": "Red Bull",
                "Time": "1:20.726",
                "Gap": "+0.465",
                "Laps": "22"
            },
            {
                "Pos.": "4",
                "Driver": "#44Lewis Hamilton",
                "Constructor": "Mercedes",
                "Time": "1:20.769",
                "Gap": "+0.508",
                "Laps": "23"
            },
            {
                "Pos.": "5",
                "Driver": "#7Kimi Räikkönen",
                "Constructor": "Ferrari",
                "Time": "1:20.859",
                "Gap": "+0.598",
                "Laps": "18"
            },
            {
                "Pos.": "6",
                "Driver": "#5Sebastian Vettel",
                "Constructor": "Ferrari",
                "Time": "1:21.185",
                "Gap": "+0.924",
                "Laps": "22"
            },
            {
                "Pos.": "7",
                "Driver": "#14Fernando Alonso",
                "Constructor": "McLaren",
                "Time": "1:21.584",
                "Gap": "+1.323",
                "Laps": "11"
            },
            {
                "Pos.": "8",
                "Driver": "#77Valtteri Bottas",
                "Constructor": "Williams",
                "Time": "1:21.649",
                "Gap": "+1.388",
                "Laps": "21"
            },
            {
                "Pos.": "9",
                "Driver": "#11Sergio Pérez",
                "Constructor": "Force India",
                "Time": "1:21.672",
                "Gap": "+1.411",
                "Laps": "22"
            },
            {
                "Pos.": "10",
                "Driver": "#30Jolyon Palmer",
                "Constructor": "Renault",
                "Time": "1:21.935",
                "Gap": "+1.674",
                "Laps": "19"
            },
            {
                "Pos.": "11",
                "Driver": "#19Felipe Massa",
                "Constructor": "Williams",
                "Time": "1:21.975",
                "Gap": "+1.714",
                "Laps": "28"
            },
            {
                "Pos.": "12",
                "Driver": "#20Kevin Magnussen",
                "Constructor": "Renault",
                "Time": "1:21.989",
                "Gap": "+1.728",
                "Laps": "13"
            },
            {
                "Pos.": "13",
                "Driver": "#22Jenson Button",
                "Constructor": "McLaren",
                "Time": "1:22.009",
                "Gap": "+1.748",
                "Laps": "11"
            },
            {
                "Pos.": "14",
                "Driver": "#21Esteban Gutiérrez",
                "Constructor": "Haas",
                "Time": "1:22.142",
                "Gap": "+1.881",
                "Laps": "15"
            },
            {
                "Pos.": "15",
                "Driver": "#8Romain Grosjean",
                "Constructor": "Haas",
                "Time": "1:22.284",
                "Gap": "+2.023",
                "Laps": "13"
            },
            {
                "Pos.": "16",
                "Driver": "#55Carlos Sainz Jr.",
                "Constructor": "Toro Rosso",
                "Time": "1:22.402",
                "Gap": "+2.141",
                "Laps": "21"
            },
            {
                "Pos.": "17",
                "Driver": "#27Nico Hülkenberg",
                "Constructor": "Force India",
                "Time": "1:22.427",
                "Gap": "+2.166",
                "Laps": "22"
            },
            {
                "Pos.": "18",
                "Driver": "#26Daniil Kvyat",
                "Constructor": "Toro Rosso",
                "Time": "1:22.541",
                "Gap": "+2.280",
                "Laps": "18"
            },
            {
                "Pos.": "19",
                "Driver": "#12Felipe Nasr",
                "Constructor": "Sauber",
                "Time": "1:22.816",
                "Gap": "+2.555",
                "Laps": "23"
            },
            {
                "Pos.": "20",
                "Driver": "#9Marcus Ericsson",
                "Constructor": "Sauber",
                "Time": "1:23.219",
                "Gap": "+2.958",
                "Laps": "23"
            },
            {
                "Pos.": "21",
                "Driver": "#94Pascal Wehrlein",
                "Constructor": "Manor",
                "Time": "1:23.311",
                "Gap": "+3.050",
                "Laps": "24"
            },
            {
                "Pos.": "22",
                "Driver": "#88Rio Haryanto",
                "Constructor": "Manor",
                "Time": "1:23.513",
                "Gap": "+3.252",
                "Laps": "23"
            }
        ],
        "free_practice_2": [
            {
                "Pos.": "1",
                "Driver": "#6Nico Rosberg",
                "Constructor": "Mercedes",
                "Time": "1:20.435",
                "Gap": "",
                "Laps": "45"
            },
            {
                "Pos.": "2",
                "Driver": "#3Daniel Ricciardo",
                "Constructor": "Red Bull",
                "Time": "1:21.030",
                "Gap": "+0.595",
                "Laps": "36"
            },
            {
                "Pos.": "3",
                "Driver": "#5Sebastian Vettel",
                "Constructor": "Ferrari",
                "Time": "1:21.348",
                "Gap": "+0.913",
                "Laps": "31"
            },
            {
                "Pos.": "4",
                "Driver": "#33Max Verstappen",
                "Constructor": "Red Bull",
                "Time": "1:21.770",
                "Gap": "+1.335",
                "Laps": "35"
            },
            {
                "Pos.": "5",
                "Driver": "#44Lewis Hamilton",
                "Constructor": "Mercedes",
                "Time": "1:21.960",
                "Gap": "+1.525",
                "Laps": "4"
            },
            {
                "Pos.": "6",
                "Driver": "#7Kimi Räikkönen",
                "Constructor": "Ferrari",
                "Time": "1:22.058",
                "Gap": "+1.623",
                "Laps": "46"
            },
            {
                "Pos.": "7",
                "Driver": "#14Fernando Alonso",
                "Constructor": "McLaren",
                "Time": "1:22.328",
                "Gap": "+1.893",
                "Laps": "21"
            },
            {
                "Pos.": "8",
                "Driver": "#22Jenson Button",
                "Constructor": "McLaren",
                "Time": "1:22.387",
                "Gap": "+1.952",
                "Laps": "34"
            },
            {
                "Pos.": "9",
                "Driver": "#27Nico Hülkenberg",
                "Constructor": "Force India",
                "Time": "1:22.449",
                "Gap": "+2.014",
                "Laps": "41"
            },
            {
                "Pos.": "10",
                "Driver": "#11Sergio Pérez",
                "Constructor": "Force India",
                "Time": "1:22.653",
                "Gap": "+2.218",
                "Laps": "38"
            },
            {
                "Pos.": "11",
                "Driver": "#21Esteban Gutiérrez",
                "Constructor": "Haas",
                "Time": "1:22.673",
                "Gap": "+2.238",
                "Laps": "38"
            },
            {
                "Pos.": "12",
                "Driver": "#19Felipe Massa",
                "Constructor": "Williams",
                "Time": "1:22.681",
                "Gap": "+2.246",
                "Laps": "39"
            },
            {
                "Pos.": "13",
                "Driver": "#55Carlos Sainz Jr.",
                "Constructor": "Toro Rosso",
                "Time": "1:22.689",
                "Gap": "+2.254",
                "Laps": "24"
            },
            {
                "Pos.": "14",
                "Driver": "#77Valtteri Bottas",
                "Constructor": "Williams",
                "Time": "1:22.773",
                "Gap": "+2.338",
                "Laps": "38"
            },
            {
                "Pos.": "15",
                "Driver": "#8Romain Grosjean",
                "Constructor": "Haas",
                "Time": "1:22.864",
                "Gap": "+2.429",
                "Laps": "28"
            },
            {
                "Pos.": "16",
                "Driver": "#26Daniil Kvyat",
                "Constructor": "Toro Rosso",
                "Time": "1:22.948",
                "Gap": "+2.513",
                "Laps": "43"
            },
            {
                "Pos.": "17",
                "Driver": "#20Kevin Magnussen",
                "Constructor": "Renault",
                "Time": "1:23.347",
                "Gap": "+2.912",
                "Laps": "41"
            },
            {
                "Pos.": "18",
                "Driver": "#9Marcus Ericsson",
                "Constructor": "Sauber",
                "Time": "1:23.437",
                "Gap": "+3.002",
                "Laps": "36"
            },
            {
                "Pos.": "19",
                "Driver": "#30Jolyon Palmer",
                "Constructor": "Renault",
                "Time": "1:23.528",
                "Gap": "+3.093",
                "Laps": "12"
            },
            {
                "Pos.": "20",
                "Driver": "#12Felipe Nasr",
                "Constructor": "Sauber",
                "Time": "1:23.986",
                "Gap": "+3.551",
                "Laps": "31"
            },
            {
                "Pos.": "21",
                "Driver": "#94Pascal Wehrlein",
                "Constructor": "Manor",
                "Time": "1:23.992",
                "Gap": "+3.557",
                "Laps": "22"
            },
            {
                "Pos.": "22",
                "Driver": "#88Rio Haryanto",
                "Constructor": "Manor",
                "Time": "1:24.265",
                "Gap": "+3.830",
                "Laps": "36"
            }
        ],
        "free_practice_1": [
            {
                "Pos.": "1",
                "Driver": "#44Lewis Hamilton",
                "Constructor": "Mercedes",
                "Time": "1:21.347",
                "Gap": "",
                "Laps": "34"
            },
            {
                "Pos.": "2",
                "Driver": "#6Nico Rosberg",
                "Constructor": "Mercedes",
                "Time": "1:21.584",
                "Gap": "+0.237",
                "Laps": "34"
            },
            {
                "Pos.": "3",
                "Driver": "#5Sebastian Vettel",
                "Constructor": "Ferrari",
                "Time": "1:22.991",
                "Gap": "+1.644",
                "Laps": "22"
            },
            {
                "Pos.": "4",
                "Driver": "#7Kimi Räikkönen",
                "Constructor": "Ferrari",
                "Time": "1:23.082",
                "Gap": "+1.735",
                "Laps": "19"
            },
            {
                "Pos.": "5",
                "Driver": "#3Daniel Ricciardo",
                "Constructor": "Red Bull",
                "Time": "1:23.174",
                "Gap": "+1.827",
                "Laps": "28"
            },
            {
                "Pos.": "6",
                "Driver": "#33Max Verstappen",
                "Constructor": "Red Bull",
                "Time": "1:23.457",
                "Gap": "+2.110",
                "Laps": "27"
            },
            {
                "Pos.": "7",
                "Driver": "#14Fernando Alonso",
                "Constructor": "McLaren",
                "Time": "1:23.935",
                "Gap": "+2.588",
                "Laps": "28"
            },
            {
                "Pos.": "8",
                "Driver": "#22Jenson Button",
                "Constructor": "McLaren",
                "Time": "1:23.961",
                "Gap": "+2.614",
                "Laps": "18"
            },
            {
                "Pos.": "9",
                "Driver": "#8Romain Grosjean",
                "Constructor": "Haas",
                "Time": "1:24.013",
                "Gap": "+2.666",
                "Laps": "22"
            },
            {
                "Pos.": "10",
                "Driver": "#11Sergio Pérez",
                "Constructor": "Force India",
                "Time": "1:24.073",
                "Gap": "+2.726",
                "Laps": "29"
            },
            {
                "Pos.": "11",
                "Driver": "#27Nico Hülkenberg",
                "Constructor": "Force India",
                "Time": "1:24.120",
                "Gap": "+2.773",
                "Laps": "29"
            },
            {
                "Pos.": "12",
                "Driver": "#19Felipe Massa",
                "Constructor": "Williams",
                "Time": "1:24.154",
                "Gap": "+2.807",
                "Laps": "27"
            },
            {
                "Pos.": "13",
                "Driver": "#77Valtteri Bottas",
                "Constructor": "Williams",
                "Time": "1:24.370",
                "Gap": "+3.023",
                "Laps": "33"
            },
            {
                "Pos.": "14",
                "Driver": "#55Carlos Sainz Jr.",
                "Constructor": "Toro Rosso",
                "Time": "1:24.579",
                "Gap": "+3.232",
                "Laps": "27"
            },
            {
                "Pos.": "15",
                "Driver": "#9Marcus Ericsson",
                "Constructor": "Sauber",
                "Time": "1:24.981",
                "Gap": "+3.634",
                "Laps": "19"
            },
            {
                "Pos.": "16",
                "Driver": "#50Charles Leclerc",
                "Constructor": "Haas",
                "Time": "1:25.181",
                "Gap": "+3.834",
                "Laps": "22"
            },
            {
                "Pos.": "17",
                "Driver": "#12Felipe Nasr",
                "Constructor": "Sauber",
                "Time": "1:25.256",
                "Gap": "+3.909",
                "Laps": "18"
            },
            {
                "Pos.": "18",
                "Driver": "#45Esteban Ocon",
                "Constructor": "Renault",
                "Time": "1:25.260",
                "Gap": "+3.913",
                "Laps": "28"
            },
            {
                "Pos.": "19",
                "Driver": "#26Daniil Kvyat",
                "Constructor": "Toro Rosso",
                "Time": "1:25.324",
                "Gap": "+3.977",
                "Laps": "16"
            },
            {
                "Pos.": "20",
                "Driver": "#88Rio Haryanto",
                "Constructor": "Manor",
                "Time": "1:27.012",
                "Gap": "+5.665",
                "Laps": "23"
            },
            {
                "Pos.": "21",
                "Driver": "#94Pascal Wehrlein",
                "Constructor": "Manor",
                "Time": "1:27.249",
                "Gap": "+5.902",
                "Laps": "9"
            },
            {
                "Pos.": "22",
                "Driver": "#30Jolyon Palmer",
                "Constructor": "Renault",
                "Time": "1:28.560",
                "Gap": "+7.213",
                "Laps": "6"
            }
        ],
        "fastest_laps": [
            {
                "Pos.": "1",
                "Driver": "#7Kimi Räikkönen",
                "Constructor": "Ferrari",
                "Time": "1:23.086",
                "Gap": "",
                "Lap": "52"
            },
            {
                "Pos.": "2",
                "Driver": "#6Nico Rosberg",
                "Constructor": "Mercedes",
                "Time": "1:23.670",
                "Gap": "+0.584",
                "Lap": "60"
            },
            {
                "Pos.": "3",
                "Driver": "#44Lewis Hamilton",
                "Constructor": "Mercedes",
                "Time": "1:23.849",
                "Gap": "+0.763",
                "Lap": "69"
            },
            {
                "Pos.": "4",
                "Driver": "#5Sebastian Vettel",
                "Constructor": "Ferrari",
                "Time": "1:24.383",
                "Gap": "+1.297",
                "Lap": "59"
            },
            {
                "Pos.": "5",
                "Driver": "#3Daniel Ricciardo",
                "Constructor": "Red Bull",
                "Time": "1:24.608",
                "Gap": "+1.522",
                "Lap": "60"
            },
            {
                "Pos.": "6",
                "Driver": "#26Daniil Kvyat",
                "Constructor": "Toro Rosso",
                "Time": "1:24.669",
                "Gap": "+1.583",
                "Lap": "48"
            },
            {
                "Pos.": "7",
                "Driver": "#33Max Verstappen",
                "Constructor": "Red Bull",
                "Time": "1:24.687",
                "Gap": "+1.601",
                "Lap": "40"
            },
            {
                "Pos.": "8",
                "Driver": "#14Fernando Alonso",
                "Constructor": "McLaren",
                "Time": "1:24.958",
                "Gap": "+1.872",
                "Lap": "62"
            },
            {
                "Pos.": "9",
                "Driver": "#11Sergio Pérez",
                "Constructor": "Force India",
                "Time": "1:25.021",
                "Gap": "+1.935",
                "Lap": "65"
            },
            {
                "Pos.": "10",
                "Driver": "#55Carlos Sainz Jr.",
                "Constructor": "Toro Rosso",
                "Time": "1:25.103",
                "Gap": "+2.017",
                "Lap": "67"
            },
            {
                "Pos.": "11",
                "Driver": "#77Valtteri Bottas",
                "Constructor": "Williams",
                "Time": "1:25.273",
                "Gap": "+2.187",
                "Lap": "59"
            },
            {
                "Pos.": "12",
                "Driver": "#19Felipe Massa",
                "Constructor": "Williams",
                "Time": "1:25.296",
                "Gap": "+2.210",
                "Lap": "68"
            },
            {
                "Pos.": "13",
                "Driver": "#27Nico Hülkenberg",
                "Constructor": "Force India",
                "Time": "1:25.392",
                "Gap": "+2.306",
                "Lap": "69"
            },
            {
                "Pos.": "14",
                "Driver": "#9Marcus Ericsson",
                "Constructor": "Sauber",
                "Time": "1:25.475",
                "Gap": "+2.389",
                "Lap": "47"
            },
            {
                "Pos.": "15",
                "Driver": "#12Felipe Nasr",
                "Constructor": "Sauber",
                "Time": "1:25.676",
                "Gap": "+2.590",
                "Lap": "66"
            },
            {
                "Pos.": "16",
                "Driver": "#30Jolyon Palmer",
                "Constructor": "Renault",
                "Time": "1:25.743",
                "Gap": "+2.657",
                "Lap": "41"
            },
            {
                "Pos.": "17",
                "Driver": "#21Esteban Gutiérrez",
                "Constructor": "Haas",
                "Time": "1:25.955",
                "Gap": "+2.869",
                "Lap": "39"
            },
            {
                "Pos.": "18",
                "Driver": "#8Romain Grosjean",
                "Constructor": "Haas",
                "Time": "1:25.958",
                "Gap": "+2.872",
                "Lap": "56"
            },
            {
                "Pos.": "19",
                "Driver": "#20Kevin Magnussen",
                "Constructor": "Renault",
                "Time": "1:26.230",
                "Gap": "+3.144",
                "Lap": "39"
            },
            {
                "Pos.": "20",
                "Driver": "#94Pascal Wehrlein",
                "Constructor": "Manor",
                "Time": "1:26.524",
                "Gap": "+3.438",
                "Lap": "47"
            },
            {
                "Pos.": "21",
                "Driver": "#22Jenson Button",
                "Constructor": "McLaren",
                "Time": "1:26.744",
                "Gap": "+3.658",
                "Lap": "9"
            },
            {
                "Pos.": "22",
                "Driver": "#88Rio Haryanto",
                "Constructor": "Manor",
                "Time": "1:27.791",
                "Gap": "+4.705",
                "Lap": "64"
            }
        ],
        "driver_of_the_day": [
            {
                "Pos.": "1",
                "Driver": "#7Kimi Räikkönen",
                "Constructor": "Ferrari",
                "Percentage": ""
            }
        ],
        "driver": [
            {
                "Pos.": "1",
                "Driver": "Lewis Hamilton",
                "Constructor": "Mercedes",
                "Wins": "5",
                "Podiums": "8",
                "Points": "192",
                "Gap": ""
            },
            {
                "Pos.": "2",
                "Driver": "Nico Rosberg",
                "Constructor": "Mercedes",
                "Wins": "5",
                "Podiums": "7",
                "Points": "186",
                "Gap": "-6"
            },
            {
                "Pos.": "3",
                "Driver": "Daniel Ricciardo",
                "Constructor": "Red Bull",
                "Wins": "0",
                "Podiums": "2",
                "Points": "115",
                "Gap": "-77"
            },
            {
                "Pos.": "4",
                "Driver": "Kimi Räikkönen",
                "Constructor": "Ferrari",
                "Wins": "0",
                "Podiums": "4",
                "Points": "114",
                "Gap": "-78"
            },
            {
                "Pos.": "5",
                "Driver": "Sebastian Vettel",
                "Constructor": "Ferrari",
                "Wins": "0",
                "Podiums": "5",
                "Points": "110",
                "Gap": "-82"
            },
            {
                "Pos.": "6",
                "Driver": "Max Verstappen",
                "Constructor": "Red Bull",
                "Wins": "1",
                "Podiums": "3",
                "Points": "100",
                "Gap": "-92"
            },
            {
                "Pos.": "7",
                "Driver": "Valtteri Bottas",
                "Constructor": "Williams",
                "Wins": "0",
                "Podiums": "1",
                "Points": "56",
                "Gap": "-136"
            },
            {
                "Pos.": "8",
                "Driver": "Sergio Pérez",
                "Constructor": "Force India",
                "Wins": "0",
                "Podiums": "2",
                "Points": "47",
                "Gap": "-145"
            },
            {
                "Pos.": "9",
                "Driver": "Felipe Massa",
                "Constructor": "Williams",
                "Wins": "0",
                "Podiums": "0",
                "Points": "38",
                "Gap": "-154"
            },
            {
                "Pos.": "10",
                "Driver": "Carlos Sainz Jr.",
                "Constructor": "Toro Rosso",
                "Wins": "0",
                "Podiums": "0",
                "Points": "30",
                "Gap": "-162"
            },
            {
                "Pos.": "11",
                "Driver": "Romain Grosjean",
                "Constructor": "Haas",
                "Wins": "0",
                "Podiums": "0",
                "Points": "28",
                "Gap": "-164"
            },
            {
                "Pos.": "12",
                "Driver": "Nico Hülkenberg",
                "Constructor": "Force India",
                "Wins": "0",
                "Podiums": "0",
                "Points": "27",
                "Gap": "-165"
            },
            {
                "Pos.": "13",
                "Driver": "Fernando Alonso",
                "Constructor": "McLaren",
                "Wins": "0",
                "Podiums": "0",
                "Points": "24",
                "Gap": "-168"
            },
            {
                "Pos.": "14",
                "Driver": "Daniil Kvyat",
                "Constructor": "Toro Rosso",
                "Wins": "0",
                "Podiums": "1",
                "Points": "23",
                "Gap": "-169"
            },
            {
                "Pos.": "15",
                "Driver": "Jenson Button",
                "Constructor": "McLaren",
                "Wins": "0",
                "Podiums": "0",
                "Points": "13",
                "Gap": "-179"
            },
            {
                "Pos.": "16",
                "Driver": "Kevin Magnussen",
                "Constructor": "Renault",
                "Wins": "0",
                "Podiums": "0",
                "Points": "6",
                "Gap": "-186"
            },
            {
                "Pos.": "17",
                "Driver": "Pascal Wehrlein",
                "Constructor": "Manor",
                "Wins": "0",
                "Podiums": "0",
                "Points": "1",
                "Gap": "-191"
            },
            {
                "Pos.": "18",
                "Driver": "Stoffel Vandoorne",
                "Constructor": "McLaren",
                "Wins": "0",
                "Podiums": "0",
                "Points": "1",
                "Gap": "-191"
            },
            {
                "Pos.": "19",
                "Driver": "Esteban Gutiérrez",
                "Constructor": "Haas",
                "Wins": "0",
                "Podiums": "0",
                "Points": "0",
                "Gap": "-192"
            },
            {
                "Pos.": "20",
                "Driver": "Jolyon Palmer",
                "Constructor": "Renault",
                "Wins": "0",
                "Podiums": "0",
                "Points": "0",
                "Gap": "-192"
            },
            {
                "Pos.": "21",
                "Driver": "Marcus Ericsson",
                "Constructor": "Sauber",
                "Wins": "0",
                "Podiums": "0",
                "Points": "0",
                "Gap": "-192"
            },
            {
                "Pos.": "22",
                "Driver": "Felipe Nasr",
                "Constructor": "Sauber",
                "Wins": "0",
                "Podiums": "0",
                "Points": "0",
                "Gap": "-192"
            },
            {
                "Pos.": "23",
                "Driver": "Rio Haryanto",
                "Constructor": "Manor",
                "Wins": "0",
                "Podiums": "0",
                "Points": "0",
                "Gap": "-192"
            }
        ],
        "constructor": [
            {
                "Pos.": "1",
                "Constructor": "Mercedes",
                "Engine": "Mercedes",
                "Wins": "10",
                "Podiums": "15",
                "Points": "378",
                "Gap": ""
            },
            {
                "Pos.": "2",
                "Constructor": "Ferrari",
                "Engine": "Ferrari",
                "Wins": "0",
                "Podiums": "9",
                "Points": "224",
                "Gap": "-154"
            },
            {
                "Pos.": "3",
                "Constructor": "Red Bull",
                "Engine": "TAG Heuer",
                "Wins": "1",
                "Podiums": "6",
                "Points": "223",
                "Gap": "-155"
            },
            {
                "Pos.": "4",
                "Constructor": "Williams",
                "Engine": "Mercedes",
                "Wins": "0",
                "Podiums": "1",
                "Points": "94",
                "Gap": "-284"
            },
            {
                "Pos.": "5",
                "Constructor": "Force India",
                "Engine": "Mercedes",
                "Wins": "0",
                "Podiums": "2",
                "Points": "74",
                "Gap": "-304"
            },
            {
                "Pos.": "6",
                "Constructor": "Toro Rosso",
                "Engine": "Ferrari",
                "Wins": "0",
                "Podiums": "0",
                "Points": "45",
                "Gap": "-333"
            },
            {
                "Pos.": "7",
                "Constructor": "McLaren",
                "Engine": "Honda",
                "Wins": "0",
                "Podiums": "0",
                "Points": "38",
                "Gap": "-340"
            },
            {
                "Pos.": "8",
                "Constructor": "Haas",
                "Engine": "Ferrari",
                "Wins": "0",
                "Podiums": "0",
                "Points": "28",
                "Gap": "-350"
            },
            {
                "Pos.": "9",
                "Constructor": "Renault",
                "Engine": "Renault",
                "Wins": "0",
                "Podiums": "0",
                "Points": "6",
                "Gap": "-372"
            },
            {
                "Pos.": "10",
                "Constructor": "Manor",
                "Engine": "Mercedes",
                "Wins": "0",
                "Podiums": "0",
                "Points": "1",
                "Gap": "-377"
            },
            {
                "Pos.": "11",
                "Constructor": "Sauber",
                "Engine": "Ferrari",
                "Wins": "0",
                "Podiums": "0",
                "Points": "0",
                "Gap": "-378"
            },
            {
                "Year": "2024",
                "Winner": "#81Oscar Piastri",
                "2nd": "Lando Norris",
                "3rd": "Lewis Hamilton",
                "Fastest lap": "1:20.305 - George Russell",
                "Pole position": "Lando Norris"
            },
            {
                "Year": "2023",
                "Winner": "#1Max Verstappen",
                "2nd": "Lando Norris",
                "3rd": "Sergio Pérez",
                "Fastest lap": "1:20.504 - Max Verstappen",
                "Pole position": "Lewis Hamilton"
            },
            {
                "Year": "2022",
                "Winner": "#1Max Verstappen",
                "2nd": "Lewis Hamilton",
                "3rd": "George Russell",
                "Fastest lap": "1:21.386 - Lewis Hamilton",
                "Pole position": "George Russell"
            },
            {
                "Year": "2021",
                "Winner": "#31Esteban Ocon",
                "2nd": "Lewis Hamilton",
                "3rd": "Carlos Sainz Jr.",
                "Fastest lap": "1:18.394 - Pierre Gasly",
                "Pole position": "Lewis Hamilton"
            },
            {
                "Year": "2020",
                "Winner": "#44Lewis Hamilton",
                "2nd": "Max Verstappen",
                "3rd": "Valtteri Bottas",
                "Fastest lap": "1:16.627 - Lewis Hamilton",
                "Pole position": "Lewis Hamilton"
            },
            {
                "Year": "2019",
                "Winner": "#44Lewis Hamilton",
                "2nd": "Max Verstappen",
                "3rd": "Sebastian Vettel",
                "Fastest lap": "1:17.103 - Max Verstappen",
                "Pole position": "Max Verstappen"
            },
            {
                "Year": "2018",
                "Winner": "#44Lewis Hamilton",
                "2nd": "Sebastian Vettel",
                "3rd": "Kimi Räikkönen",
                "Fastest lap": "1:20.012 - Daniel Ricciardo",
                "Pole position": "Lewis Hamilton"
            },
            {
                "Year": "2017",
                "Winner": "#5Sebastian Vettel",
                "2nd": "Kimi Räikkönen",
                "3rd": "Valtteri Bottas",
                "Fastest lap": "1:20.182 - Fernando Alonso",
                "Pole position": "Sebastian Vettel"
            },
            {
                "Year": "2015",
                "Winner": "#5Sebastian Vettel",
                "2nd": "Daniil Kvyat",
                "3rd": "Daniel Ricciardo",
                "Fastest lap": "1:24.821 - Daniel Ricciardo",
                "Pole position": "Lewis Hamilton"
            },
            {
                "Year": "2014",
                "Winner": "#3Daniel Ricciardo",
                "2nd": "Fernando Alonso",
                "3rd": "Lewis Hamilton",
                "Fastest lap": "1:25.724 - Nico Rosberg",
                "Pole position": "Nico Rosberg"
            },
            {
                "Year": "2013",
                "Winner": "#10Lewis Hamilton",
                "2nd": "Kimi Räikkönen",
                "3rd": "Sebastian Vettel",
                "Fastest lap": "1:24.069 - Mark Webber",
                "Pole position": "Lewis Hamilton"
            },
            {
                "Year": "2012",
                "Winner": "#4Lewis Hamilton",
                "2nd": "Kimi Räikkönen",
                "3rd": "Romain Grosjean",
                "Fastest lap": "1:24.136 - Sebastian Vettel",
                "Pole position": "Lewis Hamilton"
            },
            {
                "Year": "2011",
                "Winner": "#4Jenson Button",
                "2nd": "Sebastian Vettel",
                "3rd": "Fernando Alonso",
                "Fastest lap": "1:23.415 - Felipe Massa",
                "Pole position": "Sebastian Vettel"
            },
            {
                "Year": "2010",
                "Winner": "#6Mark Webber",
                "2nd": "Fernando Alonso",
                "3rd": "Sebastian Vettel",
                "Fastest lap": "1:22.362 - Sebastian Vettel",
                "Pole position": "Sebastian Vettel"
            },
            {
                "Year": "2009",
                "Winner": "#1Lewis Hamilton",
                "2nd": "Kimi Räikkönen",
                "3rd": "Mark Webber",
                "Fastest lap": "1:21.931 - Mark Webber",
                "Pole position": "Fernando Alonso"
            },
            {
                "Year": "2008",
                "Winner": "#23Heikki Kovalainen",
                "2nd": "Timo Glock",
                "3rd": "Kimi Räikkönen",
                "Fastest lap": "1:21.195 - Kimi Räikkönen",
                "Pole position": "Lewis Hamilton"
            },
            {
                "Year": "2007",
                "Winner": "#2Lewis Hamilton",
                "2nd": "Kimi Räikkönen",
                "3rd": "Nick Heidfeld",
                "Fastest lap": "1:20.047 - Kimi Räikkönen",
                "Pole position": "Lewis Hamilton"
            },
            {
                "Year": "2006",
                "Winner": "#12Jenson Button",
                "2nd": "Pedro de la Rosa",
                "3rd": "Nick Heidfeld",
                "Fastest lap": "1:23.516 - Felipe Massa",
                "Pole position": "Kimi Räikkönen"
            },
            {
                "Year": "2005",
                "Winner": "#9Kimi Räikkönen",
                "2nd": "Michael Schumacher",
                "3rd": "Ralf Schumacher",
                "Fastest lap": "1:21.219 - Kimi Räikkönen",
                "Pole position": "Michael Schumacher"
            },
            {
                "Year": "2004",
                "Winner": "#1Michael Schumacher",
                "2nd": "Rubens Barrichello",
                "3rd": "Fernando Alonso",
                "Fastest lap": "1:19.071 - Michael Schumacher",
                "Pole position": "Michael Schumacher"
            },
            {
                "Year": "2003",
                "Winner": "#8Fernando Alonso",
                "2nd": "Kimi Räikkönen",
                "3rd": "Juan Pablo Montoya",
                "Fastest lap": "1:22.095 - Juan Pablo Montoya",
                "Pole position": "Fernando Alonso"
            },
            {
                "Year": "2002",
                "Winner": "#2Rubens Barrichello",
                "2nd": "Michael Schumacher",
                "3rd": "Ralf Schumacher",
                "Fastest lap": "1:16.207 - Michael Schumacher",
                "Pole position": "Rubens Barrichello"
            },
            {
                "Year": "2001",
                "Winner": "#1Michael Schumacher",
                "2nd": "Rubens Barrichello",
                "3rd": "David Coulthard",
                "Fastest lap": "1:16.723 - Mika Häkkinen",
                "Pole position": "Michael Schumacher"
            },
            {
                "Year": "2000",
                "Winner": "#1Mika Häkkinen",
                "2nd": "Michael Schumacher",
                "3rd": "David Coulthard",
                "Fastest lap": "1:20.028 - Mika Häkkinen",
                "Pole position": "Michael Schumacher"
            },
            {
                "Year": "1999",
                "Winner": "#1Mika Häkkinen",
                "2nd": "David Coulthard",
                "3rd": "Eddie Irvine",
                "Fastest lap": "1:20.699 - David Coulthard",
                "Pole position": "Mika Häkkinen"
            },
            {
                "Year": "1998",
                "Winner": "#3Michael Schumacher",
                "2nd": "David Coulthard",
                "3rd": "Jacques Villeneuve",
                "Fastest lap": "1:19.286 - Michael Schumacher",
                "Pole position": "Mika Häkkinen"
            },
            {
                "Year": "1997",
                "Winner": "#3Jacques Villeneuve",
                "2nd": "Damon Hill",
                "3rd": "Johnny Herbert",
                "Fastest lap": "1:18.372 - Heinz-Harald Frentzen",
                "Pole position": "Michael Schumacher"
            },
            {
                "Year": "1996",
                "Winner": "#6Jacques Villeneuve",
                "2nd": "Damon Hill",
                "3rd": "Jean Alesi",
                "Fastest lap": "1:20.093 - Damon Hill",
                "Pole position": "Michael Schumacher"
            },
            {
                "Year": "1995",
                "Winner": "#5Damon Hill",
                "2nd": "David Coulthard",
                "3rd": "Gerhard Berger",
                "Fastest lap": "1:20.247 - Damon Hill",
                "Pole position": "Damon Hill"
            },
            {
                "Year": "1994",
                "Winner": "#5Michael Schumacher",
                "2nd": "Damon Hill",
                "3rd": "Jos Verstappen",
                "Fastest lap": "1:20.881 - Michael Schumacher",
                "Pole position": "Michael Schumacher"
            },
            {
                "Year": "1993",
                "Winner": "#0Damon Hill",
                "2nd": "Riccardo Patrese",
                "3rd": "Gerhard Berger",
                "Fastest lap": "1:19.633 - Alain Prost",
                "Pole position": "Alain Prost"
            },
            {
                "Year": "1992",
                "Winner": "#1Ayrton Senna",
                "2nd": "Nigel Mansell",
                "3rd": "Gerhard Berger",
                "Fastest lap": "1:18.308 - Nigel Mansell",
                "Pole position": "Riccardo Patrese"
            },
            {
                "Year": "1991",
                "Winner": "#1Ayrton Senna",
                "2nd": "Nigel Mansell",
                "3rd": "Riccardo Patrese",
                "Fastest lap": "1:21.547 - Bertrand Gachot",
                "Pole position": "Ayrton Senna"
            },
            {
                "Year": "1990",
                "Winner": "#5Thierry Boutsen",
                "2nd": "Ayrton Senna",
                "3rd": "Nelson Piquet",
                "Fastest lap": "1:22.058 - Riccardo Patrese",
                "Pole position": "Thierry Boutsen"
            },
            {
                "Year": "1989",
                "Winner": "#27Nigel Mansell",
                "2nd": "Ayrton Senna",
                "3rd": "Thierry Boutsen",
                "Fastest lap": "1:22.637 - Nigel Mansell",
                "Pole position": "Riccardo Patrese"
            },
            {
                "Year": "1988",
                "Winner": "#12Ayrton Senna",
                "2nd": "Alain Prost",
                "3rd": "Thierry Boutsen",
                "Fastest lap": "1:30.639 - Alain Prost",
                "Pole position": "Ayrton Senna"
            },
            {
                "Year": "1987",
                "Winner": "#6Nelson Piquet",
                "2nd": "Ayrton Senna",
                "3rd": "Alain Prost",
                "Fastest lap": "1:30.149 - Nelson Piquet",
                "Pole position": "Nigel Mansell"
            },
            {
                "Year": "1986",
                "Winner": "#6Nelson Piquet",
                "2nd": "Ayrton Senna",
                "3rd": "Nigel Mansell",
                "Fastest lap": "1:31.001 - Nelson Piquet",
                "Pole position": "Ayrton Senna"
            }
        ]
    }
}