{
    "title": "1970 South African Grand Prix | Pitwall",
    "race_name": "1970South African Grand Prix",
    "round": "1/13",
    "date": "Mar 7, 1970 at 00:00 CET",
    "location": "Midrand, South Africa",
    "circuit": "Kyalami Racing Circuit",
    "circuit_length": "4.104 m",
    "race_distance": "328.32 km (80 laps)",
    "performance": {
        "winner": "Brabham",
        "winning_time": "1:49:34.600",
        "pole_position": "Stewart",
        "fastest_lap": "Surtees",
        "fastest_lap_time": "1:20.800"
    },
    "results": {
        "race": [
            {
                "Pos.": "1",
                "Driver": "#12Jack Brabham",
                "Constructor": "Brabham",
                "Time/Retired": "1:49:34.600",
                "Grid": "3rd",
                "Laps": "80",
                "Points": "9"
            },
            {
                "Pos.": "2",
                "Driver": "#6Denny Hulme",
                "Constructor": "McLaren",
                "Time/Retired": "+8.100",
                "Grid": "6th",
                "Laps": "80",
                "Points": "6"
            },
            {
                "Pos.": "3",
                "Driver": "#1Jackie Stewart",
                "Constructor": "March",
                "Time/Retired": "+17.100",
                "Grid": "1st",
                "Laps": "80",
                "Points": "4"
            },
            {
                "Pos.": "4",
                "Driver": "#3Jean-Pierre Beltoise",
                "Constructor": "Matra",
                "Time/Retired": "+1:13.100",
                "Grid": "8th",
                "Laps": "80",
                "Points": "3"
            },
            {
                "Pos.": "5",
                "Driver": "#10John Miles",
                "Constructor": "Lotus",
                "Time/Retired": "+1 lap",
                "Grid": "14th",
                "Laps": "79",
                "Points": "2"
            },
            {
                "Pos.": "6",
                "Driver": "#11Graham Hill",
                "Constructor": "Lotus",
                "Time/Retired": "+1 lap",
                "Grid": "19th",
                "Laps": "79",
                "Points": "1"
            },
            {
                "Pos.": "7",
                "Driver": "#4Henri Pescarolo",
                "Constructor": "Matra",
                "Time/Retired": "+2 laps",
                "Grid": "18th",
                "Laps": "78",
                "Points": ""
            },
            {
                "Pos.": "8",
                "Driver": "#23John Love",
                "Constructor": "Lotus",
                "Time/Retired": "+2 laps",
                "Grid": "22nd",
                "Laps": "78",
                "Points": ""
            },
            {
                "Pos.": "9",
                "Driver": "#20Pedro Rodríguez",
                "Constructor": "BRM",
                "Time/Retired": "+4 laps",
                "Grid": "16th",
                "Laps": "76",
                "Points": ""
            },
            {
                "Pos.": "10",
                "Driver": "#16Jo Siffert",
                "Constructor": "March",
                "Time/Retired": "+5 laps",
                "Grid": "9th",
                "Laps": "75",
                "Points": ""
            },
            {
                "Pos.": "11",
                "Driver": "#24Peter de Klerk",
                "Constructor": "Brabham",
                "Time/Retired": "+5 laps",
                "Grid": "21st",
                "Laps": "75",
                "Points": ""
            },
            {
                "Pos.": "12",
                "Driver": "#25Dave Charlton",
                "Constructor": "Lotus",
                "Time/Retired": "Engine",
                "Grid": "13th",
                "Laps": "73",
                "Points": ""
            },
            {
                "Pos.": "13",
                "Driver": "#9Jochen Rindt",
                "Constructor": "Lotus",
                "Time/Retired": "Engine",
                "Grid": "4th",
                "Laps": "72",
                "Points": ""
            },
            {
                "Pos.": "DNF",
                "Driver": "#7John Surtees",
                "Constructor": "McLaren",
                "Time/Retired": "Engine",
                "Grid": "7th",
                "Laps": "60",
                "Points": ""
            },
            {
                "Pos.": "DNF",
                "Driver": "#17Jacky Ickx",
                "Constructor": "Ferrari",
                "Time/Retired": "Engine",
                "Grid": "5th",
                "Laps": "60",
                "Points": ""
            },
            {
                "Pos.": "DNF",
                "Driver": "#21George Eaton",
                "Constructor": "BRM",
                "Time/Retired": "Engine",
                "Grid": "23rd",
                "Laps": "58",
                "Points": ""
            },
            {
                "Pos.": "DNF",
                "Driver": "#2Johnny Servoz-Gavin",
                "Constructor": "March",
                "Time/Retired": "Engine",
                "Grid": "17th",
                "Laps": "57",
                "Points": ""
            },
            {
                "Pos.": "DNF",
                "Driver": "#22Piers Courage",
                "Constructor": "De Tomaso",
                "Time/Retired": "Accident",
                "Grid": "20th",
                "Laps": "39",
                "Points": ""
            },
            {
                "Pos.": "DNF",
                "Driver": "#5Bruce McLaren",
                "Constructor": "McLaren",
                "Time/Retired": "Engine",
                "Grid": "10th",
                "Laps": "39",
                "Points": ""
            },
            {
                "Pos.": "DNF",
                "Driver": "#8Mario Andretti",
                "Constructor": "March",
                "Time/Retired": "Overheating",
                "Grid": "11th",
                "Laps": "26",
                "Points": ""
            },
            {
                "Pos.": "DNF",
                "Driver": "#14Rolf Stommelen",
                "Constructor": "Brabham",
                "Time/Retired": "Engine",
                "Grid": "15th",
                "Laps": "23",
                "Points": ""
            },
            {
                "Pos.": "DNF",
                "Driver": "#19Jackie Oliver",
                "Constructor": "BRM",
                "Time/Retired": "Gearbox",
                "Grid": "12th",
                "Laps": "22",
                "Points": ""
            },
            {
                "Pos.": "DNF",
                "Driver": "#15Chris Amon",
                "Constructor": "March",
                "Time/Retired": "Overheating",
                "Grid": "2nd",
                "Laps": "14",
                "Points": ""
            }
        ],
        "qualifying": [
            {
                "Pos.": "1",
                "Driver": "#1Jackie Stewart",
                "Constructor": "March",
                "Time": "1:19.300",
                "Gap": ""
            },
            {
                "Pos.": "2",
                "Driver": "#15Chris Amon",
                "Constructor": "March",
                "Time": "1:19.300",
                "Gap": "+0.000"
            },
            {
                "Pos.": "3",
                "Driver": "#12Jack Brabham",
                "Constructor": "Brabham",
                "Time": "1:19.600",
                "Gap": "+0.300"
            },
            {
                "Pos.": "4",
                "Driver": "#9Jochen Rindt",
                "Constructor": "Lotus",
                "Time": "1:19.900",
                "Gap": "+0.600"
            },
            {
                "Pos.": "5",
                "Driver": "#17Jacky Ickx",
                "Constructor": "Ferrari",
                "Time": "1:20.000",
                "Gap": "+0.700"
            },
            {
                "Pos.": "6",
                "Driver": "#6Denny Hulme",
                "Constructor": "McLaren",
                "Time": "1:20.100",
                "Gap": "+0.800"
            },
            {
                "Pos.": "7",
                "Driver": "#7John Surtees",
                "Constructor": "McLaren",
                "Time": "1:20.200",
                "Gap": "+0.900"
            },
            {
                "Pos.": "8",
                "Driver": "#3Jean-Pierre Beltoise",
                "Constructor": "Matra",
                "Time": "1:20.200",
                "Gap": "+0.900"
            },
            {
                "Pos.": "9",
                "Driver": "#16Jo Siffert",
                "Constructor": "March",
                "Time": "1:20.200",
                "Gap": "+0.900"
            },
            {
                "Pos.": "10",
                "Driver": "#5Bruce McLaren",
                "Constructor": "McLaren",
                "Time": "1:20.300",
                "Gap": "+1.000"
            },
            {
                "Pos.": "11",
                "Driver": "#8Mario Andretti",
                "Constructor": "March",
                "Time": "1:20.500",
                "Gap": "+1.200"
            },
            {
                "Pos.": "12",
                "Driver": "#19Jackie Oliver",
                "Constructor": "BRM",
                "Time": "1:20.900",
                "Gap": "+1.600"
            },
            {
                "Pos.": "13",
                "Driver": "#25Dave Charlton",
                "Constructor": "Lotus",
                "Time": "1:20.900",
                "Gap": "+1.600"
            },
            {
                "Pos.": "14",
                "Driver": "#10John Miles",
                "Constructor": "Lotus",
                "Time": "1:21.000",
                "Gap": "+1.700"
            },
            {
                "Pos.": "15",
                "Driver": "#14Rolf Stommelen",
                "Constructor": "Brabham",
                "Time": "1:21.200",
                "Gap": "+1.900"
            },
            {
                "Pos.": "16",
                "Driver": "#20Pedro Rodríguez",
                "Constructor": "BRM",
                "Time": "1:21.300",
                "Gap": "+2.000"
            },
            {
                "Pos.": "17",
                "Driver": "#2Johnny Servoz-Gavin",
                "Constructor": "March",
                "Time": "1:21.400",
                "Gap": "+2.100"
            },
            {
                "Pos.": "18",
                "Driver": "#4Henri Pescarolo",
                "Constructor": "Matra",
                "Time": "1:21.500",
                "Gap": "+2.200"
            },
            {
                "Pos.": "19",
                "Driver": "#11Graham Hill",
                "Constructor": "Lotus",
                "Time": "1:21.600",
                "Gap": "+2.300"
            },
            {
                "Pos.": "20",
                "Driver": "#22Piers Courage",
                "Constructor": "De Tomaso",
                "Time": "1:22.000",
                "Gap": "+2.700"
            },
            {
                "Pos.": "21",
                "Driver": "#24Peter de Klerk",
                "Constructor": "Brabham",
                "Time": "1:22.700",
                "Gap": "+3.400"
            },
            {
                "Pos.": "22",
                "Driver": "#23John Love",
                "Constructor": "Lotus",
                "Time": "1:23.100",
                "Gap": "+3.800"
            },
            {
                "Pos.": "23",
                "Driver": "#21George Eaton",
                "Constructor": "BRM",
                "Time": "1:24.400",
                "Gap": "+5.100"
            }
        ],
        "fastest_laps": [
            {
                "Pos.": "1",
                "Driver": "#12Jack Brabham",
                "Constructor": "Brabham",
                "Time": "1:20.800",
                "Gap": "+0.000",
                "Lap": "71"
            },
            {
                "Pos.": "1",
                "Driver": "#7John Surtees",
                "Constructor": "McLaren",
                "Time": "1:20.800",
                "Gap": "",
                "Lap": "6"
            }
        ],
        "driver": [
            {
                "Pos.": "1",
                "Driver": "Jack Brabham",
                "Constructor": "Brabham",
                "Wins": "1",
                "Podiums": "1",
                "Points": "9",
                "Gap": ""
            },
            {
                "Pos.": "2",
                "Driver": "Denny Hulme",
                "Constructor": "McLaren",
                "Wins": "0",
                "Podiums": "1",
                "Points": "6",
                "Gap": "-3"
            },
            {
                "Pos.": "3",
                "Driver": "Jackie Stewart",
                "Constructor": "March",
                "Wins": "0",
                "Podiums": "1",
                "Points": "4",
                "Gap": "-5"
            },
            {
                "Pos.": "4",
                "Driver": "Jean-Pierre Beltoise",
                "Constructor": "Matra",
                "Wins": "0",
                "Podiums": "0",
                "Points": "3",
                "Gap": "-6"
            },
            {
                "Pos.": "5",
                "Driver": "John Miles",
                "Constructor": "Lotus",
                "Wins": "0",
                "Podiums": "0",
                "Points": "2",
                "Gap": "-7"
            },
            {
                "Pos.": "6",
                "Driver": "Graham Hill",
                "Constructor": "Lotus",
                "Wins": "0",
                "Podiums": "0",
                "Points": "1",
                "Gap": "-8"
            }
        ],
        "constructor": [
            {
                "Pos.": "1",
                "Constructor": "Brabham",
                "Engine": "Ford",
                "Wins": "1",
                "Podiums": "1",
                "Points": "9",
                "Gap": ""
            },
            {
                "Pos.": "2",
                "Constructor": "McLaren",
                "Engine": "Ford",
                "Wins": "0",
                "Podiums": "1",
                "Points": "6",
                "Gap": "-3"
            },
            {
                "Pos.": "3",
                "Constructor": "March",
                "Engine": "Ford",
                "Wins": "0",
                "Podiums": "1",
                "Points": "4",
                "Gap": "-5"
            },
            {
                "Pos.": "4",
                "Constructor": "Matra",
                "Engine": "Matra",
                "Wins": "0",
                "Podiums": "0",
                "Points": "3",
                "Gap": "-6"
            },
            {
                "Pos.": "5",
                "Constructor": "Lotus",
                "Engine": "Ford",
                "Wins": "0",
                "Podiums": "0",
                "Points": "2",
                "Gap": "-7"
            },
            {
                "Year": "1993",
                "Winner": "#2Alain Prost",
                "2nd": "Ayrton Senna",
                "3rd": "Mark Blundell",
                "Fastest lap": "1:19.492 - Alain Prost",
                "Pole position": "Alain Prost"
            },
            {
                "Year": "1992",
                "Winner": "#5Nigel Mansell",
                "2nd": "Riccardo Patrese",
                "3rd": "Ayrton Senna",
                "Fastest lap": "1:17.578 - Nigel Mansell",
                "Pole position": "Nigel Mansell"
            },
            {
                "Year": "1985",
                "Winner": "#5Nigel Mansell",
                "2nd": "Keke Rosberg",
                "3rd": "Alain Prost",
                "Fastest lap": "1:08.149 - Keke Rosberg",
                "Pole position": "Nigel Mansell"
            },
            {
                "Year": "1984",
                "Winner": "#8Niki Lauda",
                "2nd": "Alain Prost",
                "3rd": "Derek Warwick",
                "Fastest lap": "1:08.877 - Patrick Tambay",
                "Pole position": "Nelson Piquet"
            },
            {
                "Year": "1983",
                "Winner": "#6Riccardo Patrese",
                "2nd": "Andrea de Cesaris",
                "3rd": "Nelson Piquet",
                "Fastest lap": "1:09.948 - Nelson Piquet",
                "Pole position": "Patrick Tambay"
            },
            {
                "Year": "1982",
                "Winner": "#15Alain Prost",
                "2nd": "Carlos Reutemann",
                "3rd": "René Arnoux",
                "Fastest lap": "1:08.278 - Alain Prost",
                "Pole position": "René Arnoux"
            },
            {
                "Year": "1980",
                "Winner": "#16René Arnoux",
                "2nd": "Jacques Laffite",
                "3rd": "Didier Pironi",
                "Fastest lap": "1:13.150 - René Arnoux",
                "Pole position": "Jean-Pierre Jabouille"
            },
            {
                "Year": "1979",
                "Winner": "#12Gilles Villeneuve",
                "2nd": "Jody Scheckter",
                "3rd": "Jean-Pierre Jarier",
                "Fastest lap": "1:14.412 - Gilles Villeneuve",
                "Pole position": "Jean-Pierre Jabouille"
            },
            {
                "Year": "1978",
                "Winner": "#6Ronnie Peterson",
                "2nd": "Patrick Depailler",
                "3rd": "John Watson",
                "Fastest lap": "1:17.090 - Mario Andretti",
                "Pole position": "Niki Lauda"
            },
            {
                "Year": "1977",
                "Winner": "#11Niki Lauda",
                "2nd": "Jody Scheckter",
                "3rd": "Patrick Depailler",
                "Fastest lap": "1:17.630 - John Watson",
                "Pole position": "James Hunt"
            },
            {
                "Year": "1976",
                "Winner": "#1Niki Lauda",
                "2nd": "James Hunt",
                "3rd": "Jochen Mass",
                "Fastest lap": "1:17.970 - Niki Lauda",
                "Pole position": "James Hunt"
            },
            {
                "Year": "1975",
                "Winner": "#3Jody Scheckter",
                "2nd": "Carlos Reutemann",
                "3rd": "Patrick Depailler",
                "Fastest lap": "1:17.200 - Carlos Pace",
                "Pole position": "Carlos Pace"
            },
            {
                "Year": "1974",
                "Winner": "#7Carlos Reutemann",
                "2nd": "Jean-Pierre Beltoise",
                "3rd": "Mike Hailwood",
                "Fastest lap": "1:18.160 - Carlos Reutemann",
                "Pole position": "Niki Lauda"
            },
            {
                "Year": "1973",
                "Winner": "#3Jackie Stewart",
                "2nd": "Peter Revson",
                "3rd": "Emerson Fittipaldi",
                "Fastest lap": "1:17.100 - Emerson Fittipaldi",
                "Pole position": "Denny Hulme"
            },
            {
                "Year": "1972",
                "Winner": "#12Denny Hulme",
                "2nd": "Emerson Fittipaldi",
                "3rd": "Peter Revson",
                "Fastest lap": "1:18.900 - Mike Hailwood",
                "Pole position": "Jackie Stewart"
            },
            {
                "Year": "1971",
                "Winner": "#6Mario Andretti",
                "2nd": "Jackie Stewart",
                "3rd": "Clay Regazzoni",
                "Fastest lap": "1:20.300 - Mario Andretti",
                "Pole position": "Jackie Stewart"
            },
            {
                "Year": "1969",
                "Winner": "#7Jackie Stewart",
                "2nd": "Graham Hill",
                "3rd": "Denny Hulme",
                "Fastest lap": "1:21.600 - Jackie Stewart",
                "Pole position": "Jack Brabham"
            },
            {
                "Year": "1968",
                "Winner": "#4Jim Clark",
                "2nd": "Graham Hill",
                "3rd": "Jochen Rindt",
                "Fastest lap": "1:23.700 - Jim Clark",
                "Pole position": "Jim Clark"
            },
            {
                "Year": "1967",
                "Winner": "#4Pedro Rodríguez",
                "2nd": "John Love",
                "3rd": "John Surtees",
                "Fastest lap": "1:29.900 - Denny Hulme",
                "Pole position": "Jack Brabham"
            },
            {
                "Year": "1965",
                "Winner": "#5Jim Clark",
                "2nd": "John Surtees",
                "3rd": "Graham Hill",
                "Fastest lap": "1:27.600 - Jim Clark",
                "Pole position": "Jim Clark"
            },
            {
                "Year": "1963",
                "Winner": "#1Jim Clark",
                "2nd": "Dan Gurney",
                "3rd": "Graham Hill",
                "Fastest lap": "1:29.100 - Dan Gurney",
                "Pole position": "Jim Clark"
            },
            {
                "Year": "1962",
                "Winner": "#3Graham Hill",
                "2nd": "Bruce McLaren",
                "3rd": "Tony Maggs",
                "Fastest lap": "1:31.000 - Jim Clark",
                "Pole position": "Jim Clark"
            }
        ]
    }
}